<?xml version='1.0' encoding='UTF-8'?>
<GateDocument version="3">
<!-- The document's features-->

<GateDocumentFeatures>
<Feature>
  <Name className="java.lang.String">gate.SourceURL</Name>
  <Value className="java.lang.String">file:/home/leon/gate-extras/gate-twitter/experiments/ner/judgments/H/H2000.json</Value>
</Feature>
<Feature>
  <Name className="java.lang.String">mimeType</Name>
  <Value className="java.lang.String">text/x-json-twitter</Value>
</Feature>
</GateDocumentFeatures>
<!-- The document content area with serialized nodes -->

<TextWithNodes><Node id="0"/>"<Node id="1"/>You<Node id="4"/> <Node id="5"/>do<Node id="7"/>n<Node id="8"/>'t<Node id="10"/> <Node id="11"/>go<Node id="13"/> <Node id="14"/>Jessica<Node id="21"/> <Node id="22"/>Simpson<Node id="29"/> <Node id="30"/>when<Node id="34"/> <Node id="35"/>you<Node id="38"/>'<Node id="39"/>ve<Node id="41"/> <Node id="42"/>got<Node id="45"/> <Node id="46"/>Rihanna<Node id="53"/>"<Node id="54"/> <Node id="55"/>-<Node id="56"/>OITNB<Node id="61"/> <Node id="62"/>😂<Node id="64"/>
<Node id="65"/>
<Node id="66"/></TextWithNodes>
<!-- The default annotation set -->

<AnnotationSet>
</AnnotationSet>

<!-- Named annotation set -->

<AnnotationSet Name="crowdDisputed">
</AnnotationSet>

<!-- Named annotation set -->

<AnnotationSet Name="crowdResults">
<Annotation Id="128" Type="Person" StartNode="14" EndNode="21">
<Feature>
  <Name className="java.lang.String">trust</Name>
  <Value className="java.lang.Double">1.0</Value>
</Feature>
<Feature>
  <Name className="java.lang.String">cf_judgment</Name>
  <Value className="java.lang.Long">1492849612</Value>
</Feature>
<Feature>
  <Name className="java.lang.String">worker_id</Name>
  <Value className="java.lang.Long">570167</Value>
</Feature>
</Annotation>
<Annotation Id="129" Type="Person" StartNode="22" EndNode="29">
<Feature>
  <Name className="java.lang.String">trust</Name>
  <Value className="java.lang.Double">1.0</Value>
</Feature>
<Feature>
  <Name className="java.lang.String">cf_judgment</Name>
  <Value className="java.lang.Long">1492849612</Value>
</Feature>
<Feature>
  <Name className="java.lang.String">worker_id</Name>
  <Value className="java.lang.Long">570167</Value>
</Feature>
</Annotation>
<Annotation Id="130" Type="Person" StartNode="46" EndNode="53">
<Feature>
  <Name className="java.lang.String">trust</Name>
  <Value className="java.lang.Double">1.0</Value>
</Feature>
<Feature>
  <Name className="java.lang.String">cf_judgment</Name>
  <Value className="java.lang.Long">1492849612</Value>
</Feature>
<Feature>
  <Name className="java.lang.String">worker_id</Name>
  <Value className="java.lang.Long">570167</Value>
</Feature>
</Annotation>
<Annotation Id="131" Type="Organization" StartNode="56" EndNode="61">
<Feature>
  <Name className="java.lang.String">trust</Name>
  <Value className="java.lang.Double">1.0</Value>
</Feature>
<Feature>
  <Name className="java.lang.String">cf_judgment</Name>
  <Value className="java.lang.Long">1967925539</Value>
</Feature>
<Feature>
  <Name className="java.lang.String">worker_id</Name>
  <Value className="java.lang.Long">31671536</Value>
</Feature>
</Annotation>
<Annotation Id="116" Type="Person" StartNode="14" EndNode="21">
<Feature>
  <Name className="java.lang.String">trust</Name>
  <Value className="java.lang.Double">1.0</Value>
</Feature>
<Feature>
  <Name className="java.lang.String">cf_judgment</Name>
  <Value className="java.lang.Long">1492849278</Value>
</Feature>
<Feature>
  <Name className="java.lang.String">worker_id</Name>
  <Value className="java.lang.Long">30353892</Value>
</Feature>
</Annotation>
<Annotation Id="117" Type="Person" StartNode="22" EndNode="29">
<Feature>
  <Name className="java.lang.String">trust</Name>
  <Value className="java.lang.Double">1.0</Value>
</Feature>
<Feature>
  <Name className="java.lang.String">cf_judgment</Name>
  <Value className="java.lang.Long">1492849278</Value>
</Feature>
<Feature>
  <Name className="java.lang.String">worker_id</Name>
  <Value className="java.lang.Long">30353892</Value>
</Feature>
</Annotation>
<Annotation Id="118" Type="Person" StartNode="46" EndNode="53">
<Feature>
  <Name className="java.lang.String">trust</Name>
  <Value className="java.lang.Double">1.0</Value>
</Feature>
<Feature>
  <Name className="java.lang.String">cf_judgment</Name>
  <Value className="java.lang.Long">1492849278</Value>
</Feature>
<Feature>
  <Name className="java.lang.String">worker_id</Name>
  <Value className="java.lang.Long">30353892</Value>
</Feature>
</Annotation>
<Annotation Id="119" Type="Person" StartNode="14" EndNode="21">
<Feature>
  <Name className="java.lang.String">trust</Name>
  <Value className="java.lang.Double">1.0</Value>
</Feature>
<Feature>
  <Name className="java.lang.String">cf_judgment</Name>
  <Value className="java.lang.Long">1492849326</Value>
</Feature>
<Feature>
  <Name className="java.lang.String">worker_id</Name>
  <Value className="java.lang.Long">25419319</Value>
</Feature>
</Annotation>
<Annotation Id="120" Type="Person" StartNode="22" EndNode="29">
<Feature>
  <Name className="java.lang.String">trust</Name>
  <Value className="java.lang.Double">1.0</Value>
</Feature>
<Feature>
  <Name className="java.lang.String">cf_judgment</Name>
  <Value className="java.lang.Long">1492849326</Value>
</Feature>
<Feature>
  <Name className="java.lang.String">worker_id</Name>
  <Value className="java.lang.Long">25419319</Value>
</Feature>
</Annotation>
<Annotation Id="121" Type="Person" StartNode="46" EndNode="53">
<Feature>
  <Name className="java.lang.String">trust</Name>
  <Value className="java.lang.Double">1.0</Value>
</Feature>
<Feature>
  <Name className="java.lang.String">cf_judgment</Name>
  <Value className="java.lang.Long">1492849326</Value>
</Feature>
<Feature>
  <Name className="java.lang.String">worker_id</Name>
  <Value className="java.lang.Long">25419319</Value>
</Feature>
</Annotation>
<Annotation Id="122" Type="Person" StartNode="14" EndNode="21">
<Feature>
  <Name className="java.lang.String">trust</Name>
  <Value className="java.lang.Double">1.0</Value>
</Feature>
<Feature>
  <Name className="java.lang.String">cf_judgment</Name>
  <Value className="java.lang.Long">1492849358</Value>
</Feature>
<Feature>
  <Name className="java.lang.String">worker_id</Name>
  <Value className="java.lang.Long">29335044</Value>
</Feature>
</Annotation>
<Annotation Id="123" Type="Person" StartNode="22" EndNode="29">
<Feature>
  <Name className="java.lang.String">trust</Name>
  <Value className="java.lang.Double">1.0</Value>
</Feature>
<Feature>
  <Name className="java.lang.String">cf_judgment</Name>
  <Value className="java.lang.Long">1492849358</Value>
</Feature>
<Feature>
  <Name className="java.lang.String">worker_id</Name>
  <Value className="java.lang.Long">29335044</Value>
</Feature>
</Annotation>
<Annotation Id="124" Type="Person" StartNode="46" EndNode="53">
<Feature>
  <Name className="java.lang.String">trust</Name>
  <Value className="java.lang.Double">1.0</Value>
</Feature>
<Feature>
  <Name className="java.lang.String">cf_judgment</Name>
  <Value className="java.lang.Long">1492849358</Value>
</Feature>
<Feature>
  <Name className="java.lang.String">worker_id</Name>
  <Value className="java.lang.Long">29335044</Value>
</Feature>
</Annotation>
<Annotation Id="125" Type="Person" StartNode="14" EndNode="21">
<Feature>
  <Name className="java.lang.String">trust</Name>
  <Value className="java.lang.Double">1.0</Value>
</Feature>
<Feature>
  <Name className="java.lang.String">cf_judgment</Name>
  <Value className="java.lang.Long">1492849375</Value>
</Feature>
<Feature>
  <Name className="java.lang.String">worker_id</Name>
  <Value className="java.lang.Long">26336767</Value>
</Feature>
</Annotation>
<Annotation Id="126" Type="Person" StartNode="22" EndNode="29">
<Feature>
  <Name className="java.lang.String">trust</Name>
  <Value className="java.lang.Double">1.0</Value>
</Feature>
<Feature>
  <Name className="java.lang.String">cf_judgment</Name>
  <Value className="java.lang.Long">1492849375</Value>
</Feature>
<Feature>
  <Name className="java.lang.String">worker_id</Name>
  <Value className="java.lang.Long">26336767</Value>
</Feature>
</Annotation>
<Annotation Id="127" Type="Person" StartNode="46" EndNode="53">
<Feature>
  <Name className="java.lang.String">trust</Name>
  <Value className="java.lang.Double">1.0</Value>
</Feature>
<Feature>
  <Name className="java.lang.String">cf_judgment</Name>
  <Value className="java.lang.Long">1492849375</Value>
</Feature>
<Feature>
  <Name className="java.lang.String">worker_id</Name>
  <Value className="java.lang.Long">26336767</Value>
</Feature>
</Annotation>
</AnnotationSet>

<!-- Named annotation set -->

<AnnotationSet Name="Original markups">
<Annotation Id="1" Type="Tweet" StartNode="0" EndNode="65">
<Feature>
  <Name className="java.lang.String">user:screen_name</Name>
  <Value className="java.lang.String">glazedoanut</Value>
</Feature>
<Feature>
  <Name className="java.lang.String">truncated</Name>
  <Value className="java.lang.Boolean">false</Value>
</Feature>
<Feature>
  <Name className="java.lang.String">user:location</Name>
  <Value className="java.lang.String"></Value>
</Feature>
<Feature>
  <Name className="java.lang.String">source</Name>
  <Value className="java.lang.String">&lt;a href="http://twitter.com/download/iphone" rel="nofollow">Twitter for iPhone&lt;/a></Value>
</Feature>
<Feature>
  <Name className="java.lang.String">id_str</Name>
  <Value className="java.lang.String">476948547539988480</Value>
</Feature>
</Annotation>
</AnnotationSet>

<!-- Named annotation set -->

<AnnotationSet Name="merged">
<Annotation Id="140" Type="Person" StartNode="46" EndNode="53">
</Annotation>
<Annotation Id="141" Type="Organization" StartNode="56" EndNode="61">
</Annotation>
<Annotation Id="139" Type="Person" StartNode="14" EndNode="29">
</Annotation>
</AnnotationSet>

<!-- Named annotation set -->

<AnnotationSet Name="_x">
</AnnotationSet>

<!-- Named annotation set -->

<AnnotationSet Name="maxRecall">
<Annotation Id="3" Type="Token" StartNode="0" EndNode="1">
<Feature>
  <Name className="java.lang.String">length</Name>
  <Value className="java.lang.String">1</Value>
</Feature>
<Feature>
  <Name className="java.lang.String">string</Name>
  <Value className="java.lang.String">"</Value>
</Feature>
<Feature>
  <Name className="java.lang.String">category</Name>
  <Value className="java.lang.String">''</Value>
</Feature>
<Feature>
  <Name className="java.lang.String">kind</Name>
  <Value className="java.lang.String">punctuation</Value>
</Feature>
</Annotation>
<Annotation Id="132" Type="Organization" StartNode="56" EndNode="61">
</Annotation>
<Annotation Id="4" Type="Token" StartNode="1" EndNode="4">
<Feature>
  <Name className="java.lang.String">length</Name>
  <Value className="java.lang.String">3</Value>
</Feature>
<Feature>
  <Name className="java.lang.String">orth</Name>
  <Value className="java.lang.String">upperInitial</Value>
</Feature>
<Feature>
  <Name className="java.lang.String">string</Name>
  <Value className="java.lang.String">You</Value>
</Feature>
<Feature>
  <Name className="java.lang.String">category</Name>
  <Value className="java.lang.String">PRP</Value>
</Feature>
<Feature>
  <Name className="java.lang.String">kind</Name>
  <Value className="java.lang.String">word</Value>
</Feature>
</Annotation>
<Annotation Id="133" Type="Person" StartNode="14" EndNode="21">
</Annotation>
<Annotation Id="5" Type="SpaceToken" StartNode="4" EndNode="5">
<Feature>
  <Name className="java.lang.String">string</Name>
  <Value className="java.lang.String"> </Value>
</Feature>
<Feature>
  <Name className="java.lang.String">length</Name>
  <Value className="java.lang.String">1</Value>
</Feature>
<Feature>
  <Name className="java.lang.String">kind</Name>
  <Value className="java.lang.String">space</Value>
</Feature>
</Annotation>
<Annotation Id="134" Type="Person" StartNode="22" EndNode="29">
</Annotation>
<Annotation Id="135" Type="Person" StartNode="46" EndNode="53">
</Annotation>
<Annotation Id="9" Type="SpaceToken" StartNode="10" EndNode="11">
<Feature>
  <Name className="java.lang.String">string</Name>
  <Value className="java.lang.String"> </Value>
</Feature>
<Feature>
  <Name className="java.lang.String">length</Name>
  <Value className="java.lang.String">1</Value>
</Feature>
<Feature>
  <Name className="java.lang.String">kind</Name>
  <Value className="java.lang.String">space</Value>
</Feature>
</Annotation>
<Annotation Id="10" Type="Token" StartNode="11" EndNode="13">
<Feature>
  <Name className="java.lang.String">length</Name>
  <Value className="java.lang.String">2</Value>
</Feature>
<Feature>
  <Name className="java.lang.String">orth</Name>
  <Value className="java.lang.String">lowercase</Value>
</Feature>
<Feature>
  <Name className="java.lang.String">string</Name>
  <Value className="java.lang.String">go</Value>
</Feature>
<Feature>
  <Name className="java.lang.String">category</Name>
  <Value className="java.lang.String">VB</Value>
</Feature>
<Feature>
  <Name className="java.lang.String">kind</Name>
  <Value className="java.lang.String">word</Value>
</Feature>
</Annotation>
<Annotation Id="11" Type="SpaceToken" StartNode="13" EndNode="14">
<Feature>
  <Name className="java.lang.String">string</Name>
  <Value className="java.lang.String"> </Value>
</Feature>
<Feature>
  <Name className="java.lang.String">length</Name>
  <Value className="java.lang.String">1</Value>
</Feature>
<Feature>
  <Name className="java.lang.String">kind</Name>
  <Value className="java.lang.String">space</Value>
</Feature>
</Annotation>
<Annotation Id="12" Type="Token" StartNode="14" EndNode="21">
<Feature>
  <Name className="java.lang.String">length</Name>
  <Value className="java.lang.String">7</Value>
</Feature>
<Feature>
  <Name className="java.lang.String">orth</Name>
  <Value className="java.lang.String">upperInitial</Value>
</Feature>
<Feature>
  <Name className="java.lang.String">string</Name>
  <Value className="java.lang.String">Jessica</Value>
</Feature>
<Feature>
  <Name className="java.lang.String">category</Name>
  <Value className="java.lang.String">NNP</Value>
</Feature>
<Feature>
  <Name className="java.lang.String">kind</Name>
  <Value className="java.lang.String">word</Value>
</Feature>
</Annotation>
<Annotation Id="13" Type="SpaceToken" StartNode="21" EndNode="22">
<Feature>
  <Name className="java.lang.String">string</Name>
  <Value className="java.lang.String"> </Value>
</Feature>
<Feature>
  <Name className="java.lang.String">length</Name>
  <Value className="java.lang.String">1</Value>
</Feature>
<Feature>
  <Name className="java.lang.String">kind</Name>
  <Value className="java.lang.String">space</Value>
</Feature>
</Annotation>
<Annotation Id="14" Type="Token" StartNode="22" EndNode="29">
<Feature>
  <Name className="java.lang.String">length</Name>
  <Value className="java.lang.String">7</Value>
</Feature>
<Feature>
  <Name className="java.lang.String">orth</Name>
  <Value className="java.lang.String">upperInitial</Value>
</Feature>
<Feature>
  <Name className="java.lang.String">string</Name>
  <Value className="java.lang.String">Simpson</Value>
</Feature>
<Feature>
  <Name className="java.lang.String">category</Name>
  <Value className="java.lang.String">NNP</Value>
</Feature>
<Feature>
  <Name className="java.lang.String">kind</Name>
  <Value className="java.lang.String">word</Value>
</Feature>
</Annotation>
<Annotation Id="15" Type="SpaceToken" StartNode="29" EndNode="30">
<Feature>
  <Name className="java.lang.String">string</Name>
  <Value className="java.lang.String"> </Value>
</Feature>
<Feature>
  <Name className="java.lang.String">length</Name>
  <Value className="java.lang.String">1</Value>
</Feature>
<Feature>
  <Name className="java.lang.String">kind</Name>
  <Value className="java.lang.String">space</Value>
</Feature>
</Annotation>
<Annotation Id="16" Type="Token" StartNode="30" EndNode="34">
<Feature>
  <Name className="java.lang.String">length</Name>
  <Value className="java.lang.String">4</Value>
</Feature>
<Feature>
  <Name className="java.lang.String">orth</Name>
  <Value className="java.lang.String">lowercase</Value>
</Feature>
<Feature>
  <Name className="java.lang.String">string</Name>
  <Value className="java.lang.String">when</Value>
</Feature>
<Feature>
  <Name className="java.lang.String">category</Name>
  <Value className="java.lang.String">WRB</Value>
</Feature>
<Feature>
  <Name className="java.lang.String">kind</Name>
  <Value className="java.lang.String">word</Value>
</Feature>
</Annotation>
<Annotation Id="17" Type="SpaceToken" StartNode="34" EndNode="35">
<Feature>
  <Name className="java.lang.String">string</Name>
  <Value className="java.lang.String"> </Value>
</Feature>
<Feature>
  <Name className="java.lang.String">length</Name>
  <Value className="java.lang.String">1</Value>
</Feature>
<Feature>
  <Name className="java.lang.String">kind</Name>
  <Value className="java.lang.String">space</Value>
</Feature>
</Annotation>
<Annotation Id="18" Type="Token" StartNode="35" EndNode="38">
<Feature>
  <Name className="java.lang.String">length</Name>
  <Value className="java.lang.String">3</Value>
</Feature>
<Feature>
  <Name className="java.lang.String">orth</Name>
  <Value className="java.lang.String">lowercase</Value>
</Feature>
<Feature>
  <Name className="java.lang.String">string</Name>
  <Value className="java.lang.String">you</Value>
</Feature>
<Feature>
  <Name className="java.lang.String">category</Name>
  <Value className="java.lang.String">PRP</Value>
</Feature>
<Feature>
  <Name className="java.lang.String">kind</Name>
  <Value className="java.lang.String">word</Value>
</Feature>
</Annotation>
<Annotation Id="21" Type="SpaceToken" StartNode="41" EndNode="42">
<Feature>
  <Name className="java.lang.String">string</Name>
  <Value className="java.lang.String"> </Value>
</Feature>
<Feature>
  <Name className="java.lang.String">length</Name>
  <Value className="java.lang.String">1</Value>
</Feature>
<Feature>
  <Name className="java.lang.String">kind</Name>
  <Value className="java.lang.String">space</Value>
</Feature>
</Annotation>
<Annotation Id="22" Type="Token" StartNode="42" EndNode="45">
<Feature>
  <Name className="java.lang.String">length</Name>
  <Value className="java.lang.String">3</Value>
</Feature>
<Feature>
  <Name className="java.lang.String">orth</Name>
  <Value className="java.lang.String">lowercase</Value>
</Feature>
<Feature>
  <Name className="java.lang.String">string</Name>
  <Value className="java.lang.String">got</Value>
</Feature>
<Feature>
  <Name className="java.lang.String">category</Name>
  <Value className="java.lang.String">VBD</Value>
</Feature>
<Feature>
  <Name className="java.lang.String">kind</Name>
  <Value className="java.lang.String">word</Value>
</Feature>
</Annotation>
<Annotation Id="23" Type="SpaceToken" StartNode="45" EndNode="46">
<Feature>
  <Name className="java.lang.String">string</Name>
  <Value className="java.lang.String"> </Value>
</Feature>
<Feature>
  <Name className="java.lang.String">length</Name>
  <Value className="java.lang.String">1</Value>
</Feature>
<Feature>
  <Name className="java.lang.String">kind</Name>
  <Value className="java.lang.String">space</Value>
</Feature>
</Annotation>
<Annotation Id="24" Type="Token" StartNode="46" EndNode="53">
<Feature>
  <Name className="java.lang.String">length</Name>
  <Value className="java.lang.String">7</Value>
</Feature>
<Feature>
  <Name className="java.lang.String">orth</Name>
  <Value className="java.lang.String">upperInitial</Value>
</Feature>
<Feature>
  <Name className="java.lang.String">string</Name>
  <Value className="java.lang.String">Rihanna</Value>
</Feature>
<Feature>
  <Name className="java.lang.String">category</Name>
  <Value className="java.lang.String">NNP</Value>
</Feature>
<Feature>
  <Name className="java.lang.String">kind</Name>
  <Value className="java.lang.String">word</Value>
</Feature>
</Annotation>
<Annotation Id="25" Type="Token" StartNode="53" EndNode="54">
<Feature>
  <Name className="java.lang.String">length</Name>
  <Value className="java.lang.String">1</Value>
</Feature>
<Feature>
  <Name className="java.lang.String">string</Name>
  <Value className="java.lang.String">"</Value>
</Feature>
<Feature>
  <Name className="java.lang.String">category</Name>
  <Value className="java.lang.String">''</Value>
</Feature>
<Feature>
  <Name className="java.lang.String">kind</Name>
  <Value className="java.lang.String">punctuation</Value>
</Feature>
</Annotation>
<Annotation Id="26" Type="SpaceToken" StartNode="54" EndNode="55">
<Feature>
  <Name className="java.lang.String">string</Name>
  <Value className="java.lang.String"> </Value>
</Feature>
<Feature>
  <Name className="java.lang.String">length</Name>
  <Value className="java.lang.String">1</Value>
</Feature>
<Feature>
  <Name className="java.lang.String">kind</Name>
  <Value className="java.lang.String">space</Value>
</Feature>
</Annotation>
<Annotation Id="27" Type="Token" StartNode="55" EndNode="56">
<Feature>
  <Name className="java.lang.String">length</Name>
  <Value className="java.lang.String">1</Value>
</Feature>
<Feature>
  <Name className="java.lang.String">string</Name>
  <Value className="java.lang.String">-</Value>
</Feature>
<Feature>
  <Name className="java.lang.String">category</Name>
  <Value className="java.lang.String">:</Value>
</Feature>
<Feature>
  <Name className="java.lang.String">kind</Name>
  <Value className="java.lang.String">punctuation</Value>
</Feature>
<Feature>
  <Name className="java.lang.String">subkind</Name>
  <Value className="java.lang.String">dashpunct</Value>
</Feature>
</Annotation>
<Annotation Id="28" Type="Token" StartNode="56" EndNode="61">
<Feature>
  <Name className="java.lang.String">length</Name>
  <Value className="java.lang.String">5</Value>
</Feature>
<Feature>
  <Name className="java.lang.String">orth</Name>
  <Value className="java.lang.String">allCaps</Value>
</Feature>
<Feature>
  <Name className="java.lang.String">origString</Name>
  <Value className="java.lang.String">OITNB</Value>
</Feature>
<Feature>
  <Name className="java.lang.String">string</Name>
  <Value className="java.lang.String">OITNB</Value>
</Feature>
<Feature>
  <Name className="java.lang.String">category</Name>
  <Value className="java.lang.String">NNP</Value>
</Feature>
<Feature>
  <Name className="java.lang.String">kind</Name>
  <Value className="java.lang.String">word</Value>
</Feature>
</Annotation>
<Annotation Id="29" Type="SpaceToken" StartNode="61" EndNode="62">
<Feature>
  <Name className="java.lang.String">string</Name>
  <Value className="java.lang.String"> </Value>
</Feature>
<Feature>
  <Name className="java.lang.String">length</Name>
  <Value className="java.lang.String">1</Value>
</Feature>
<Feature>
  <Name className="java.lang.String">kind</Name>
  <Value className="java.lang.String">space</Value>
</Feature>
</Annotation>
<Annotation Id="33" Type="Token" StartNode="62" EndNode="64">
<Feature>
  <Name className="java.lang.String">orth</Name>
  <Value className="java.lang.String">mixed</Value>
</Feature>
<Feature>
  <Name className="java.lang.String">string</Name>
  <Value className="java.lang.String">:')</Value>
</Feature>
<Feature>
  <Name className="java.lang.String">kind</Name>
  <Value className="java.lang.String">punctuation</Value>
</Feature>
<Feature>
  <Name className="java.lang.String">length</Name>
  <Value className="java.lang.Long">2</Value>
</Feature>
<Feature>
  <Name className="java.lang.String">rule</Name>
  <Value className="java.lang.String">RecombineEmoticon</Value>
</Feature>
<Feature>
  <Name className="java.lang.String">replaced</Name>
  <Value className="java.lang.Integer">1</Value>
</Feature>
<Feature>
  <Name className="java.lang.String">origString</Name>
  <Value className="java.lang.String">😂</Value>
</Feature>
<Feature>
  <Name className="java.lang.String">category</Name>
  <Value className="java.lang.String">UH</Value>
</Feature>
</Annotation>
<Annotation Id="35" Type="Token" StartNode="5" EndNode="7">
<Feature>
  <Name className="java.lang.String">length</Name>
  <Value className="java.lang.String">2</Value>
</Feature>
<Feature>
  <Name className="java.lang.String">orth</Name>
  <Value className="java.lang.String">lowercase</Value>
</Feature>
<Feature>
  <Name className="java.lang.String">string</Name>
  <Value className="java.lang.String">do</Value>
</Feature>
<Feature>
  <Name className="java.lang.String">category</Name>
  <Value className="java.lang.String">VBP</Value>
</Feature>
<Feature>
  <Name className="java.lang.String">kind</Name>
  <Value className="java.lang.String">word</Value>
</Feature>
</Annotation>
<Annotation Id="36" Type="Token" StartNode="7" EndNode="10">
<Feature>
  <Name className="java.lang.String">length</Name>
  <Value className="java.lang.String">3</Value>
</Feature>
<Feature>
  <Name className="java.lang.String">orth</Name>
  <Value className="java.lang.String">lowercase</Value>
</Feature>
<Feature>
  <Name className="java.lang.String">origString</Name>
  <Value className="java.lang.String">n't</Value>
</Feature>
<Feature>
  <Name className="java.lang.String">string</Name>
  <Value className="java.lang.String">not</Value>
</Feature>
<Feature>
  <Name className="java.lang.String">category</Name>
  <Value className="java.lang.String">RB</Value>
</Feature>
<Feature>
  <Name className="java.lang.String">kind</Name>
  <Value className="java.lang.String">word</Value>
</Feature>
</Annotation>
<Annotation Id="37" Type="Token" StartNode="38" EndNode="41">
<Feature>
  <Name className="java.lang.String">length</Name>
  <Value className="java.lang.String">3</Value>
</Feature>
<Feature>
  <Name className="java.lang.String">orth</Name>
  <Value className="java.lang.String">apostrophe</Value>
</Feature>
<Feature>
  <Name className="java.lang.String">origString</Name>
  <Value className="java.lang.String">'ve</Value>
</Feature>
<Feature>
  <Name className="java.lang.String">string</Name>
  <Value className="java.lang.String">Ave</Value>
</Feature>
<Feature>
  <Name className="java.lang.String">category</Name>
  <Value className="java.lang.String">NNP</Value>
</Feature>
<Feature>
  <Name className="java.lang.String">kind</Name>
  <Value className="java.lang.String">word</Value>
</Feature>
</Annotation>
<Annotation Id="38" Type="SpaceToken" StartNode="64" EndNode="65">
<Feature>
  <Name className="java.lang.String">string</Name>
  <Value className="java.lang.String">
</Value>
</Feature>
<Feature>
  <Name className="java.lang.String">length</Name>
  <Value className="java.lang.String">1</Value>
</Feature>
<Feature>
  <Name className="java.lang.String">kind</Name>
  <Value className="java.lang.String">control</Value>
</Feature>
</Annotation>
<Annotation Id="39" Type="SpaceToken" StartNode="65" EndNode="66">
<Feature>
  <Name className="java.lang.String">string</Name>
  <Value className="java.lang.String">
</Value>
</Feature>
<Feature>
  <Name className="java.lang.String">length</Name>
  <Value className="java.lang.String">1</Value>
</Feature>
<Feature>
  <Name className="java.lang.String">kind</Name>
  <Value className="java.lang.String">control</Value>
</Feature>
</Annotation>
</AnnotationSet>

<!-- Named annotation set -->

<AnnotationSet Name="Key">
<Annotation Id="1" Type="Tweet" StartNode="0" EndNode="65">
<Feature>
  <Name className="java.lang.String">user:screen_name</Name>
  <Value className="java.lang.String">glazedoanut</Value>
</Feature>
<Feature>
  <Name className="java.lang.String">Organization_unit_id</Name>
  <Value className="java.lang.Long">935253451</Value>
</Feature>
<Feature>
  <Name className="java.lang.String">id_str</Name>
  <Value className="java.lang.String">476948547539988480</Value>
</Feature>
<Feature>
  <Name className="java.lang.String">truncated</Name>
  <Value className="java.lang.Boolean">false</Value>
</Feature>
<Feature>
  <Name className="java.lang.String">user:location</Name>
  <Value className="java.lang.String"></Value>
</Feature>
<Feature>
  <Name className="java.lang.String">source</Name>
  <Value className="java.lang.String">&lt;a href="http://twitter.com/download/iphone" rel="nofollow">Twitter for iPhone&lt;/a></Value>
</Feature>
<Feature>
  <Name className="java.lang.String">lang</Name>
  <Value className="java.lang.String">english</Value>
</Feature>
<Feature>
  <Name className="java.lang.String">_unit_id</Name>
  <Value className="java.lang.Long">935253451</Value>
</Feature>
<Feature>
  <Name className="java.lang.String">Location_unit_id</Name>
  <Value className="java.lang.Long">620245535</Value>
</Feature>
<Feature>
  <Name className="java.lang.String">Person_unit_id</Name>
  <Value className="java.lang.Long">615937842</Value>
</Feature>
</Annotation>
<Annotation Id="2" Type="Lookup" StartNode="62" EndNode="64">
<Feature>
  <Name className="java.lang.String">majorType</Name>
  <Value className="java.lang.String">emoticon</Value>
</Feature>
<Feature>
  <Name className="java.lang.String">normalized</Name>
  <Value className="java.lang.String">:')</Value>
</Feature>
<Feature>
  <Name className="java.lang.String">minorType</Name>
  <Value className="java.lang.String">unicode</Value>
</Feature>
</Annotation>
<Annotation Id="3" Type="Token" StartNode="0" EndNode="1">
<Feature>
  <Name className="java.lang.String">length</Name>
  <Value className="java.lang.String">1</Value>
</Feature>
<Feature>
  <Name className="java.lang.String">string</Name>
  <Value className="java.lang.String">"</Value>
</Feature>
<Feature>
  <Name className="java.lang.String">category</Name>
  <Value className="java.lang.String">''</Value>
</Feature>
<Feature>
  <Name className="java.lang.String">kind</Name>
  <Value className="java.lang.String">punctuation</Value>
</Feature>
</Annotation>
<Annotation Id="4" Type="Token" StartNode="1" EndNode="4">
<Feature>
  <Name className="java.lang.String">length</Name>
  <Value className="java.lang.String">3</Value>
</Feature>
<Feature>
  <Name className="java.lang.String">orth</Name>
  <Value className="java.lang.String">upperInitial</Value>
</Feature>
<Feature>
  <Name className="java.lang.String">string</Name>
  <Value className="java.lang.String">You</Value>
</Feature>
<Feature>
  <Name className="java.lang.String">category</Name>
  <Value className="java.lang.String">PRP</Value>
</Feature>
<Feature>
  <Name className="java.lang.String">kind</Name>
  <Value className="java.lang.String">word</Value>
</Feature>
</Annotation>
<Annotation Id="5" Type="SpaceToken" StartNode="4" EndNode="5">
<Feature>
  <Name className="java.lang.String">string</Name>
  <Value className="java.lang.String"> </Value>
</Feature>
<Feature>
  <Name className="java.lang.String">length</Name>
  <Value className="java.lang.String">1</Value>
</Feature>
<Feature>
  <Name className="java.lang.String">kind</Name>
  <Value className="java.lang.String">space</Value>
</Feature>
</Annotation>
<Annotation Id="9" Type="SpaceToken" StartNode="10" EndNode="11">
<Feature>
  <Name className="java.lang.String">string</Name>
  <Value className="java.lang.String"> </Value>
</Feature>
<Feature>
  <Name className="java.lang.String">length</Name>
  <Value className="java.lang.String">1</Value>
</Feature>
<Feature>
  <Name className="java.lang.String">kind</Name>
  <Value className="java.lang.String">space</Value>
</Feature>
</Annotation>
<Annotation Id="10" Type="Token" StartNode="11" EndNode="13">
<Feature>
  <Name className="java.lang.String">length</Name>
  <Value className="java.lang.String">2</Value>
</Feature>
<Feature>
  <Name className="java.lang.String">orth</Name>
  <Value className="java.lang.String">lowercase</Value>
</Feature>
<Feature>
  <Name className="java.lang.String">string</Name>
  <Value className="java.lang.String">go</Value>
</Feature>
<Feature>
  <Name className="java.lang.String">category</Name>
  <Value className="java.lang.String">VB</Value>
</Feature>
<Feature>
  <Name className="java.lang.String">kind</Name>
  <Value className="java.lang.String">word</Value>
</Feature>
</Annotation>
<Annotation Id="11" Type="SpaceToken" StartNode="13" EndNode="14">
<Feature>
  <Name className="java.lang.String">string</Name>
  <Value className="java.lang.String"> </Value>
</Feature>
<Feature>
  <Name className="java.lang.String">length</Name>
  <Value className="java.lang.String">1</Value>
</Feature>
<Feature>
  <Name className="java.lang.String">kind</Name>
  <Value className="java.lang.String">space</Value>
</Feature>
</Annotation>
<Annotation Id="12" Type="Token" StartNode="14" EndNode="21">
<Feature>
  <Name className="java.lang.String">length</Name>
  <Value className="java.lang.String">7</Value>
</Feature>
<Feature>
  <Name className="java.lang.String">orth</Name>
  <Value className="java.lang.String">upperInitial</Value>
</Feature>
<Feature>
  <Name className="java.lang.String">string</Name>
  <Value className="java.lang.String">Jessica</Value>
</Feature>
<Feature>
  <Name className="java.lang.String">category</Name>
  <Value className="java.lang.String">NNP</Value>
</Feature>
<Feature>
  <Name className="java.lang.String">kind</Name>
  <Value className="java.lang.String">word</Value>
</Feature>
</Annotation>
<Annotation Id="13" Type="SpaceToken" StartNode="21" EndNode="22">
<Feature>
  <Name className="java.lang.String">string</Name>
  <Value className="java.lang.String"> </Value>
</Feature>
<Feature>
  <Name className="java.lang.String">length</Name>
  <Value className="java.lang.String">1</Value>
</Feature>
<Feature>
  <Name className="java.lang.String">kind</Name>
  <Value className="java.lang.String">space</Value>
</Feature>
</Annotation>
<Annotation Id="14" Type="Token" StartNode="22" EndNode="29">
<Feature>
  <Name className="java.lang.String">length</Name>
  <Value className="java.lang.String">7</Value>
</Feature>
<Feature>
  <Name className="java.lang.String">orth</Name>
  <Value className="java.lang.String">upperInitial</Value>
</Feature>
<Feature>
  <Name className="java.lang.String">string</Name>
  <Value className="java.lang.String">Simpson</Value>
</Feature>
<Feature>
  <Name className="java.lang.String">category</Name>
  <Value className="java.lang.String">NNP</Value>
</Feature>
<Feature>
  <Name className="java.lang.String">kind</Name>
  <Value className="java.lang.String">word</Value>
</Feature>
</Annotation>
<Annotation Id="15" Type="SpaceToken" StartNode="29" EndNode="30">
<Feature>
  <Name className="java.lang.String">string</Name>
  <Value className="java.lang.String"> </Value>
</Feature>
<Feature>
  <Name className="java.lang.String">length</Name>
  <Value className="java.lang.String">1</Value>
</Feature>
<Feature>
  <Name className="java.lang.String">kind</Name>
  <Value className="java.lang.String">space</Value>
</Feature>
</Annotation>
<Annotation Id="16" Type="Token" StartNode="30" EndNode="34">
<Feature>
  <Name className="java.lang.String">length</Name>
  <Value className="java.lang.String">4</Value>
</Feature>
<Feature>
  <Name className="java.lang.String">orth</Name>
  <Value className="java.lang.String">lowercase</Value>
</Feature>
<Feature>
  <Name className="java.lang.String">string</Name>
  <Value className="java.lang.String">when</Value>
</Feature>
<Feature>
  <Name className="java.lang.String">category</Name>
  <Value className="java.lang.String">WRB</Value>
</Feature>
<Feature>
  <Name className="java.lang.String">kind</Name>
  <Value className="java.lang.String">word</Value>
</Feature>
</Annotation>
<Annotation Id="17" Type="SpaceToken" StartNode="34" EndNode="35">
<Feature>
  <Name className="java.lang.String">string</Name>
  <Value className="java.lang.String"> </Value>
</Feature>
<Feature>
  <Name className="java.lang.String">length</Name>
  <Value className="java.lang.String">1</Value>
</Feature>
<Feature>
  <Name className="java.lang.String">kind</Name>
  <Value className="java.lang.String">space</Value>
</Feature>
</Annotation>
<Annotation Id="18" Type="Token" StartNode="35" EndNode="38">
<Feature>
  <Name className="java.lang.String">length</Name>
  <Value className="java.lang.String">3</Value>
</Feature>
<Feature>
  <Name className="java.lang.String">orth</Name>
  <Value className="java.lang.String">lowercase</Value>
</Feature>
<Feature>
  <Name className="java.lang.String">string</Name>
  <Value className="java.lang.String">you</Value>
</Feature>
<Feature>
  <Name className="java.lang.String">category</Name>
  <Value className="java.lang.String">PRP</Value>
</Feature>
<Feature>
  <Name className="java.lang.String">kind</Name>
  <Value className="java.lang.String">word</Value>
</Feature>
</Annotation>
<Annotation Id="21" Type="SpaceToken" StartNode="41" EndNode="42">
<Feature>
  <Name className="java.lang.String">string</Name>
  <Value className="java.lang.String"> </Value>
</Feature>
<Feature>
  <Name className="java.lang.String">length</Name>
  <Value className="java.lang.String">1</Value>
</Feature>
<Feature>
  <Name className="java.lang.String">kind</Name>
  <Value className="java.lang.String">space</Value>
</Feature>
</Annotation>
<Annotation Id="22" Type="Token" StartNode="42" EndNode="45">
<Feature>
  <Name className="java.lang.String">length</Name>
  <Value className="java.lang.String">3</Value>
</Feature>
<Feature>
  <Name className="java.lang.String">orth</Name>
  <Value className="java.lang.String">lowercase</Value>
</Feature>
<Feature>
  <Name className="java.lang.String">string</Name>
  <Value className="java.lang.String">got</Value>
</Feature>
<Feature>
  <Name className="java.lang.String">category</Name>
  <Value className="java.lang.String">VBD</Value>
</Feature>
<Feature>
  <Name className="java.lang.String">kind</Name>
  <Value className="java.lang.String">word</Value>
</Feature>
</Annotation>
<Annotation Id="23" Type="SpaceToken" StartNode="45" EndNode="46">
<Feature>
  <Name className="java.lang.String">string</Name>
  <Value className="java.lang.String"> </Value>
</Feature>
<Feature>
  <Name className="java.lang.String">length</Name>
  <Value className="java.lang.String">1</Value>
</Feature>
<Feature>
  <Name className="java.lang.String">kind</Name>
  <Value className="java.lang.String">space</Value>
</Feature>
</Annotation>
<Annotation Id="24" Type="Token" StartNode="46" EndNode="53">
<Feature>
  <Name className="java.lang.String">length</Name>
  <Value className="java.lang.String">7</Value>
</Feature>
<Feature>
  <Name className="java.lang.String">orth</Name>
  <Value className="java.lang.String">upperInitial</Value>
</Feature>
<Feature>
  <Name className="java.lang.String">string</Name>
  <Value className="java.lang.String">Rihanna</Value>
</Feature>
<Feature>
  <Name className="java.lang.String">category</Name>
  <Value className="java.lang.String">NNP</Value>
</Feature>
<Feature>
  <Name className="java.lang.String">kind</Name>
  <Value className="java.lang.String">word</Value>
</Feature>
</Annotation>
<Annotation Id="25" Type="Token" StartNode="53" EndNode="54">
<Feature>
  <Name className="java.lang.String">length</Name>
  <Value className="java.lang.String">1</Value>
</Feature>
<Feature>
  <Name className="java.lang.String">string</Name>
  <Value className="java.lang.String">"</Value>
</Feature>
<Feature>
  <Name className="java.lang.String">category</Name>
  <Value className="java.lang.String">''</Value>
</Feature>
<Feature>
  <Name className="java.lang.String">kind</Name>
  <Value className="java.lang.String">punctuation</Value>
</Feature>
</Annotation>
<Annotation Id="26" Type="SpaceToken" StartNode="54" EndNode="55">
<Feature>
  <Name className="java.lang.String">string</Name>
  <Value className="java.lang.String"> </Value>
</Feature>
<Feature>
  <Name className="java.lang.String">length</Name>
  <Value className="java.lang.String">1</Value>
</Feature>
<Feature>
  <Name className="java.lang.String">kind</Name>
  <Value className="java.lang.String">space</Value>
</Feature>
</Annotation>
<Annotation Id="90" Type="Lookup" StartNode="1" EndNode="4">
<Feature>
  <Name className="java.lang.String">majorType</Name>
  <Value className="java.lang.String">stop</Value>
</Feature>
</Annotation>
<Annotation Id="27" Type="Token" StartNode="55" EndNode="56">
<Feature>
  <Name className="java.lang.String">length</Name>
  <Value className="java.lang.String">1</Value>
</Feature>
<Feature>
  <Name className="java.lang.String">string</Name>
  <Value className="java.lang.String">-</Value>
</Feature>
<Feature>
  <Name className="java.lang.String">category</Name>
  <Value className="java.lang.String">:</Value>
</Feature>
<Feature>
  <Name className="java.lang.String">kind</Name>
  <Value className="java.lang.String">punctuation</Value>
</Feature>
<Feature>
  <Name className="java.lang.String">subkind</Name>
  <Value className="java.lang.String">dashpunct</Value>
</Feature>
</Annotation>
<Annotation Id="91" Type="Lookup" StartNode="5" EndNode="8">
<Feature>
  <Name className="java.lang.String">majorType</Name>
  <Value className="java.lang.String">person_first</Value>
</Feature>
<Feature>
  <Name className="java.lang.String">kind</Name>
  <Value className="java.lang.String">ambig</Value>
</Feature>
<Feature>
  <Name className="java.lang.String">minorType</Name>
  <Value className="java.lang.String">male</Value>
</Feature>
</Annotation>
<Annotation Id="92" Type="Lookup" StartNode="14" EndNode="29">
<Feature>
  <Name className="java.lang.String">gender</Name>
  <Value className="java.lang.String">female</Value>
</Feature>
<Feature>
  <Name className="java.lang.String">majorType</Name>
  <Value className="java.lang.String">person_full</Value>
</Feature>
</Annotation>
<Annotation Id="28" Type="Token" StartNode="56" EndNode="61">
<Feature>
  <Name className="java.lang.String">length</Name>
  <Value className="java.lang.String">5</Value>
</Feature>
<Feature>
  <Name className="java.lang.String">orth</Name>
  <Value className="java.lang.String">allCaps</Value>
</Feature>
<Feature>
  <Name className="java.lang.String">origString</Name>
  <Value className="java.lang.String">OITNB</Value>
</Feature>
<Feature>
  <Name className="java.lang.String">string</Name>
  <Value className="java.lang.String">OITNB</Value>
</Feature>
<Feature>
  <Name className="java.lang.String">category</Name>
  <Value className="java.lang.String">NNP</Value>
</Feature>
<Feature>
  <Name className="java.lang.String">kind</Name>
  <Value className="java.lang.String">word</Value>
</Feature>
</Annotation>
<Annotation Id="93" Type="Lookup" StartNode="22" EndNode="29">
<Feature>
  <Name className="java.lang.String">majorType</Name>
  <Value className="java.lang.String">person_first</Value>
</Feature>
<Feature>
  <Name className="java.lang.String">minorType</Name>
  <Value className="java.lang.String">male</Value>
</Feature>
</Annotation>
<Annotation Id="29" Type="SpaceToken" StartNode="61" EndNode="62">
<Feature>
  <Name className="java.lang.String">string</Name>
  <Value className="java.lang.String"> </Value>
</Feature>
<Feature>
  <Name className="java.lang.String">length</Name>
  <Value className="java.lang.String">1</Value>
</Feature>
<Feature>
  <Name className="java.lang.String">kind</Name>
  <Value className="java.lang.String">space</Value>
</Feature>
</Annotation>
<Annotation Id="94" Type="Lookup" StartNode="22" EndNode="29">
<Feature>
  <Name className="java.lang.String">majorType</Name>
  <Value className="java.lang.String">location</Value>
</Feature>
<Feature>
  <Name className="java.lang.String">minorType</Name>
  <Value className="java.lang.String">city</Value>
</Feature>
</Annotation>
<Annotation Id="95" Type="Lookup" StartNode="39" EndNode="41">
<Feature>
  <Name className="java.lang.String">majorType</Name>
  <Value className="java.lang.String">country_code</Value>
</Feature>
</Annotation>
<Annotation Id="96" Type="Lookup" StartNode="46" EndNode="53">
<Feature>
  <Name className="java.lang.String">gender</Name>
  <Value className="java.lang.String">female</Value>
</Feature>
<Feature>
  <Name className="java.lang.String">majorType</Name>
  <Value className="java.lang.String">person_full</Value>
</Feature>
</Annotation>
<Annotation Id="33" Type="Token" StartNode="62" EndNode="64">
<Feature>
  <Name className="java.lang.String">orth</Name>
  <Value className="java.lang.String">mixed</Value>
</Feature>
<Feature>
  <Name className="java.lang.String">string</Name>
  <Value className="java.lang.String">:')</Value>
</Feature>
<Feature>
  <Name className="java.lang.String">kind</Name>
  <Value className="java.lang.String">punctuation</Value>
</Feature>
<Feature>
  <Name className="java.lang.String">length</Name>
  <Value className="java.lang.Long">2</Value>
</Feature>
<Feature>
  <Name className="java.lang.String">rule</Name>
  <Value className="java.lang.String">RecombineEmoticon</Value>
</Feature>
<Feature>
  <Name className="java.lang.String">replaced</Name>
  <Value className="java.lang.Integer">1</Value>
</Feature>
<Feature>
  <Name className="java.lang.String">origString</Name>
  <Value className="java.lang.String">😂</Value>
</Feature>
<Feature>
  <Name className="java.lang.String">category</Name>
  <Value className="java.lang.String">UH</Value>
</Feature>
</Annotation>
<Annotation Id="97" Type="Lookup" StartNode="46" EndNode="53">
<Feature>
  <Name className="java.lang.String">majorType</Name>
  <Value className="java.lang.String">person_full</Value>
</Feature>
<Feature>
  <Name className="java.lang.String">minorType</Name>
  <Value className="java.lang.String">music</Value>
</Feature>
</Annotation>
<Annotation Id="34" Type="Emoticon" StartNode="62" EndNode="64">
<Feature>
  <Name className="java.lang.String">normalized</Name>
  <Value className="java.lang.String">:')</Value>
</Feature>
</Annotation>
<Annotation Id="98" Type="Split" StartNode="64" EndNode="66">
<Feature>
  <Name className="java.lang.String">kind</Name>
  <Value className="java.lang.String">external</Value>
</Feature>
</Annotation>
<Annotation Id="35" Type="Token" StartNode="5" EndNode="7">
<Feature>
  <Name className="java.lang.String">length</Name>
  <Value className="java.lang.String">2</Value>
</Feature>
<Feature>
  <Name className="java.lang.String">orth</Name>
  <Value className="java.lang.String">lowercase</Value>
</Feature>
<Feature>
  <Name className="java.lang.String">string</Name>
  <Value className="java.lang.String">do</Value>
</Feature>
<Feature>
  <Name className="java.lang.String">category</Name>
  <Value className="java.lang.String">VBP</Value>
</Feature>
<Feature>
  <Name className="java.lang.String">kind</Name>
  <Value className="java.lang.String">word</Value>
</Feature>
</Annotation>
<Annotation Id="99" Type="Sentence" StartNode="0" EndNode="64">
</Annotation>
<Annotation Id="36" Type="Token" StartNode="7" EndNode="10">
<Feature>
  <Name className="java.lang.String">length</Name>
  <Value className="java.lang.String">3</Value>
</Feature>
<Feature>
  <Name className="java.lang.String">orth</Name>
  <Value className="java.lang.String">lowercase</Value>
</Feature>
<Feature>
  <Name className="java.lang.String">origString</Name>
  <Value className="java.lang.String">n't</Value>
</Feature>
<Feature>
  <Name className="java.lang.String">string</Name>
  <Value className="java.lang.String">not</Value>
</Feature>
<Feature>
  <Name className="java.lang.String">category</Name>
  <Value className="java.lang.String">RB</Value>
</Feature>
<Feature>
  <Name className="java.lang.String">kind</Name>
  <Value className="java.lang.String">word</Value>
</Feature>
</Annotation>
<Annotation Id="37" Type="Token" StartNode="38" EndNode="41">
<Feature>
  <Name className="java.lang.String">length</Name>
  <Value className="java.lang.String">3</Value>
</Feature>
<Feature>
  <Name className="java.lang.String">orth</Name>
  <Value className="java.lang.String">apostrophe</Value>
</Feature>
<Feature>
  <Name className="java.lang.String">origString</Name>
  <Value className="java.lang.String">'ve</Value>
</Feature>
<Feature>
  <Name className="java.lang.String">string</Name>
  <Value className="java.lang.String">Ave</Value>
</Feature>
<Feature>
  <Name className="java.lang.String">category</Name>
  <Value className="java.lang.String">NNP</Value>
</Feature>
<Feature>
  <Name className="java.lang.String">kind</Name>
  <Value className="java.lang.String">word</Value>
</Feature>
</Annotation>
<Annotation Id="38" Type="SpaceToken" StartNode="64" EndNode="65">
<Feature>
  <Name className="java.lang.String">string</Name>
  <Value className="java.lang.String">
</Value>
</Feature>
<Feature>
  <Name className="java.lang.String">length</Name>
  <Value className="java.lang.String">1</Value>
</Feature>
<Feature>
  <Name className="java.lang.String">kind</Name>
  <Value className="java.lang.String">control</Value>
</Feature>
</Annotation>
<Annotation Id="39" Type="SpaceToken" StartNode="65" EndNode="66">
<Feature>
  <Name className="java.lang.String">string</Name>
  <Value className="java.lang.String">
</Value>
</Feature>
<Feature>
  <Name className="java.lang.String">length</Name>
  <Value className="java.lang.String">1</Value>
</Feature>
<Feature>
  <Name className="java.lang.String">kind</Name>
  <Value className="java.lang.String">control</Value>
</Feature>
</Annotation>
<Annotation Id="112" Type="Person" StartNode="14" EndNode="29">
<Feature>
  <Name className="java.lang.String">firstName</Name>
  <Value className="java.lang.String">Jessica</Value>
</Feature>
<Feature>
  <Name className="java.lang.String">rule</Name>
  <Value className="java.lang.String">GazPerson</Value>
</Feature>
<Feature>
  <Name className="java.lang.String">ruleFinal</Name>
  <Value className="java.lang.String">PersonFinal</Value>
</Feature>
<Feature>
  <Name className="java.lang.String">gender</Name>
  <Value className="java.lang.String">female</Value>
</Feature>
<Feature>
  <Name className="java.lang.String">surname</Name>
  <Value className="java.lang.String">Simpson</Value>
</Feature>
<Feature>
  <Name className="java.lang.String">kind</Name>
  <Value className="java.lang.String">fullName</Value>
</Feature>
</Annotation>
<Annotation Id="113" Type="Person" StartNode="46" EndNode="53">
<Feature>
  <Name className="java.lang.String">rule</Name>
  <Value className="java.lang.String">GazPerson</Value>
</Feature>
<Feature>
  <Name className="java.lang.String">ruleFinal</Name>
  <Value className="java.lang.String">PersonFinal</Value>
</Feature>
<Feature>
  <Name className="java.lang.String">gender</Name>
  <Value className="java.lang.String">female</Value>
</Feature>
<Feature>
  <Name className="java.lang.String">surname</Name>
  <Value className="java.lang.String">Rihanna</Value>
</Feature>
<Feature>
  <Name className="java.lang.String">kind</Name>
  <Value className="java.lang.String">fullName</Value>
</Feature>
</Annotation>
<Annotation Id="114" Type="Unknown" StartNode="38" EndNode="41">
<Feature>
  <Name className="java.lang.String">rule</Name>
  <Value className="java.lang.String">Unknown</Value>
</Feature>
<Feature>
  <Name className="java.lang.String">kind</Name>
  <Value className="java.lang.String">PN</Value>
</Feature>
</Annotation>
<Annotation Id="115" Type="Unknown" StartNode="56" EndNode="61">
<Feature>
  <Name className="java.lang.String">rule</Name>
  <Value className="java.lang.String">Unknown</Value>
</Feature>
<Feature>
  <Name className="java.lang.String">kind</Name>
  <Value className="java.lang.String">PN</Value>
</Feature>
</Annotation>
</AnnotationSet>

</GateDocument>
