<?xml version='1.0' encoding='UTF-8'?>
<GateDocument version="3">
<!-- The document's features-->

<GateDocumentFeatures>
<Feature>
  <Name className="java.lang.String">gate.SourceURL</Name>
  <Value className="java.lang.String">file:/home/leon/gate-extras/gate-twitter/experiments/ner/judgments/G/g-raw/nz_news.json</Value>
</Feature>
<Feature>
  <Name className="java.lang.String">mimeType</Name>
  <Value className="java.lang.String">text/x-json-twitter</Value>
</Feature>
</GateDocumentFeatures>
<!-- The document content area with serialized nodes -->

<TextWithNodes><Node id="0"/>'<Node id="1"/>Brownlee<Node id="9"/> <Node id="10"/>doing<Node id="15"/> <Node id="16"/>nothing<Node id="23"/>'<Node id="24"/> <Node id="25"/>about<Node id="30"/> <Node id="31"/>driving<Node id="38"/> <Node id="39"/>licence<Node id="46"/> <Node id="47"/>test<Node id="51"/> <Node id="52"/>failure<Node id="59"/> <Node id="60"/>rate<Node id="64"/>:<Node id="65"/> <Node id="66"/>Doing<Node id="71"/> <Node id="72"/>nothing<Node id="79"/> <Node id="80"/>about<Node id="85"/> <Node id="86"/>the<Node id="89"/> <Node id="90"/>rising<Node id="96"/> <Node id="97"/>number<Node id="103"/> <Node id="104"/>of<Node id="106"/> <Node id="107"/>peo<Node id="110"/>.<Node id="111"/>.<Node id="112"/>.<Node id="113"/> <Node id="114"/>http://t.<Node id="123"/>co<Node id="125"/>/mfKI2KayVc<Node id="136"/>
<Node id="137"/>
<Node id="138"/></TextWithNodes>
<!-- The default annotation set -->

<AnnotationSet>
</AnnotationSet>

<!-- Named annotation set -->

<AnnotationSet Name="crowdDisputed">
</AnnotationSet>

<!-- Named annotation set -->

<AnnotationSet Name="crowdResults">
<Annotation Id="189" Type="Person" StartNode="1" EndNode="9">
<Feature>
  <Name className="java.lang.String">trust</Name>
  <Value className="java.lang.Double">1.0</Value>
</Feature>
<Feature>
  <Name className="java.lang.String">cf_judgment</Name>
  <Value className="java.lang.Long">1488721223</Value>
</Feature>
<Feature>
  <Name className="java.lang.String">worker_id</Name>
  <Value className="java.lang.Long">21317536</Value>
</Feature>
</Annotation>
<Annotation Id="190" Type="Person" StartNode="1" EndNode="9">
<Feature>
  <Name className="java.lang.String">trust</Name>
  <Value className="java.lang.Double">1.0</Value>
</Feature>
<Feature>
  <Name className="java.lang.String">cf_judgment</Name>
  <Value className="java.lang.Long">1492162551</Value>
</Feature>
<Feature>
  <Name className="java.lang.String">worker_id</Name>
  <Value className="java.lang.Long">26802850</Value>
</Feature>
</Annotation>
</AnnotationSet>

<!-- Named annotation set -->

<AnnotationSet Name="Original markups">
<Annotation Id="1" Type="Tweet" StartNode="0" EndNode="137">
<Feature>
  <Name className="java.lang.String">user:screen_name</Name>
  <Value className="java.lang.String">newzealandnews</Value>
</Feature>
<Feature>
  <Name className="java.lang.String">truncated</Name>
  <Value className="java.lang.Boolean">false</Value>
</Feature>
<Feature>
  <Name className="java.lang.String">user:location</Name>
  <Value className="java.lang.String">New Zealand</Value>
</Feature>
<Feature>
  <Name className="java.lang.String">source</Name>
  <Value className="java.lang.String">&lt;a href="http://twitterfeed.com" rel="nofollow">twitterfeed&lt;/a></Value>
</Feature>
<Feature>
  <Name className="java.lang.String">id_str</Name>
  <Value className="java.lang.String">471798826898960384</Value>
</Feature>
</Annotation>
<Annotation Id="2" Type="urls" StartNode="114" EndNode="136">
<Feature>
  <Name className="java.lang.String">expanded_url</Name>
  <Value className="java.lang.String">http://nzne.ws/1nDNBxG</Value>
</Feature>
<Feature>
  <Name className="java.lang.String">display_url</Name>
  <Value className="java.lang.String">nzne.ws/1nDNBxG</Value>
</Feature>
<Feature>
  <Name className="java.lang.String">url</Name>
  <Value className="java.lang.String">http://t.co/mfKI2KayVc</Value>
</Feature>
</Annotation>
</AnnotationSet>

<!-- Named annotation set -->

<AnnotationSet Name="merged">
<Annotation Id="193" Type="Person" StartNode="1" EndNode="9">
</Annotation>
</AnnotationSet>

<!-- Named annotation set -->

<AnnotationSet Name="maxRecall">
<Annotation Id="3" Type="Token" StartNode="0" EndNode="1">
<Feature>
  <Name className="java.lang.String">length</Name>
  <Value className="java.lang.String">1</Value>
</Feature>
<Feature>
  <Name className="java.lang.String">string</Name>
  <Value className="java.lang.String">'</Value>
</Feature>
<Feature>
  <Name className="java.lang.String">category</Name>
  <Value className="java.lang.String">''</Value>
</Feature>
<Feature>
  <Name className="java.lang.String">kind</Name>
  <Value className="java.lang.String">punctuation</Value>
</Feature>
</Annotation>
<Annotation Id="4" Type="Token" StartNode="1" EndNode="9">
<Feature>
  <Name className="java.lang.String">length</Name>
  <Value className="java.lang.String">8</Value>
</Feature>
<Feature>
  <Name className="java.lang.String">orth</Name>
  <Value className="java.lang.String">upperInitial</Value>
</Feature>
<Feature>
  <Name className="java.lang.String">string</Name>
  <Value className="java.lang.String">Brownlee</Value>
</Feature>
<Feature>
  <Name className="java.lang.String">category</Name>
  <Value className="java.lang.String">NNP</Value>
</Feature>
<Feature>
  <Name className="java.lang.String">kind</Name>
  <Value className="java.lang.String">word</Value>
</Feature>
</Annotation>
<Annotation Id="5" Type="SpaceToken" StartNode="9" EndNode="10">
<Feature>
  <Name className="java.lang.String">string</Name>
  <Value className="java.lang.String"> </Value>
</Feature>
<Feature>
  <Name className="java.lang.String">length</Name>
  <Value className="java.lang.String">1</Value>
</Feature>
<Feature>
  <Name className="java.lang.String">kind</Name>
  <Value className="java.lang.String">space</Value>
</Feature>
</Annotation>
<Annotation Id="6" Type="Token" StartNode="10" EndNode="15">
<Feature>
  <Name className="java.lang.String">length</Name>
  <Value className="java.lang.String">5</Value>
</Feature>
<Feature>
  <Name className="java.lang.String">orth</Name>
  <Value className="java.lang.String">lowercase</Value>
</Feature>
<Feature>
  <Name className="java.lang.String">string</Name>
  <Value className="java.lang.String">doing</Value>
</Feature>
<Feature>
  <Name className="java.lang.String">category</Name>
  <Value className="java.lang.String">VBG</Value>
</Feature>
<Feature>
  <Name className="java.lang.String">kind</Name>
  <Value className="java.lang.String">word</Value>
</Feature>
</Annotation>
<Annotation Id="7" Type="SpaceToken" StartNode="15" EndNode="16">
<Feature>
  <Name className="java.lang.String">string</Name>
  <Value className="java.lang.String"> </Value>
</Feature>
<Feature>
  <Name className="java.lang.String">length</Name>
  <Value className="java.lang.String">1</Value>
</Feature>
<Feature>
  <Name className="java.lang.String">kind</Name>
  <Value className="java.lang.String">space</Value>
</Feature>
</Annotation>
<Annotation Id="8" Type="Token" StartNode="16" EndNode="23">
<Feature>
  <Name className="java.lang.String">length</Name>
  <Value className="java.lang.String">7</Value>
</Feature>
<Feature>
  <Name className="java.lang.String">orth</Name>
  <Value className="java.lang.String">lowercase</Value>
</Feature>
<Feature>
  <Name className="java.lang.String">string</Name>
  <Value className="java.lang.String">nothing</Value>
</Feature>
<Feature>
  <Name className="java.lang.String">category</Name>
  <Value className="java.lang.String">NN</Value>
</Feature>
<Feature>
  <Name className="java.lang.String">kind</Name>
  <Value className="java.lang.String">word</Value>
</Feature>
</Annotation>
<Annotation Id="9" Type="Token" StartNode="23" EndNode="24">
<Feature>
  <Name className="java.lang.String">length</Name>
  <Value className="java.lang.String">1</Value>
</Feature>
<Feature>
  <Name className="java.lang.String">string</Name>
  <Value className="java.lang.String">'</Value>
</Feature>
<Feature>
  <Name className="java.lang.String">category</Name>
  <Value className="java.lang.String">''</Value>
</Feature>
<Feature>
  <Name className="java.lang.String">kind</Name>
  <Value className="java.lang.String">punctuation</Value>
</Feature>
</Annotation>
<Annotation Id="10" Type="SpaceToken" StartNode="24" EndNode="25">
<Feature>
  <Name className="java.lang.String">string</Name>
  <Value className="java.lang.String"> </Value>
</Feature>
<Feature>
  <Name className="java.lang.String">length</Name>
  <Value className="java.lang.String">1</Value>
</Feature>
<Feature>
  <Name className="java.lang.String">kind</Name>
  <Value className="java.lang.String">space</Value>
</Feature>
</Annotation>
<Annotation Id="11" Type="Token" StartNode="25" EndNode="30">
<Feature>
  <Name className="java.lang.String">length</Name>
  <Value className="java.lang.String">5</Value>
</Feature>
<Feature>
  <Name className="java.lang.String">orth</Name>
  <Value className="java.lang.String">lowercase</Value>
</Feature>
<Feature>
  <Name className="java.lang.String">string</Name>
  <Value className="java.lang.String">about</Value>
</Feature>
<Feature>
  <Name className="java.lang.String">category</Name>
  <Value className="java.lang.String">IN</Value>
</Feature>
<Feature>
  <Name className="java.lang.String">kind</Name>
  <Value className="java.lang.String">word</Value>
</Feature>
</Annotation>
<Annotation Id="12" Type="SpaceToken" StartNode="30" EndNode="31">
<Feature>
  <Name className="java.lang.String">string</Name>
  <Value className="java.lang.String"> </Value>
</Feature>
<Feature>
  <Name className="java.lang.String">length</Name>
  <Value className="java.lang.String">1</Value>
</Feature>
<Feature>
  <Name className="java.lang.String">kind</Name>
  <Value className="java.lang.String">space</Value>
</Feature>
</Annotation>
<Annotation Id="13" Type="Token" StartNode="31" EndNode="38">
<Feature>
  <Name className="java.lang.String">length</Name>
  <Value className="java.lang.String">7</Value>
</Feature>
<Feature>
  <Name className="java.lang.String">orth</Name>
  <Value className="java.lang.String">lowercase</Value>
</Feature>
<Feature>
  <Name className="java.lang.String">string</Name>
  <Value className="java.lang.String">driving</Value>
</Feature>
<Feature>
  <Name className="java.lang.String">category</Name>
  <Value className="java.lang.String">VBG</Value>
</Feature>
<Feature>
  <Name className="java.lang.String">kind</Name>
  <Value className="java.lang.String">word</Value>
</Feature>
</Annotation>
<Annotation Id="14" Type="SpaceToken" StartNode="38" EndNode="39">
<Feature>
  <Name className="java.lang.String">string</Name>
  <Value className="java.lang.String"> </Value>
</Feature>
<Feature>
  <Name className="java.lang.String">length</Name>
  <Value className="java.lang.String">1</Value>
</Feature>
<Feature>
  <Name className="java.lang.String">kind</Name>
  <Value className="java.lang.String">space</Value>
</Feature>
</Annotation>
<Annotation Id="15" Type="Token" StartNode="39" EndNode="46">
<Feature>
  <Name className="java.lang.String">length</Name>
  <Value className="java.lang.String">7</Value>
</Feature>
<Feature>
  <Name className="java.lang.String">orth</Name>
  <Value className="java.lang.String">lowercase</Value>
</Feature>
<Feature>
  <Name className="java.lang.String">string</Name>
  <Value className="java.lang.String">licence</Value>
</Feature>
<Feature>
  <Name className="java.lang.String">category</Name>
  <Value className="java.lang.String">NN</Value>
</Feature>
<Feature>
  <Name className="java.lang.String">kind</Name>
  <Value className="java.lang.String">word</Value>
</Feature>
</Annotation>
<Annotation Id="16" Type="SpaceToken" StartNode="46" EndNode="47">
<Feature>
  <Name className="java.lang.String">string</Name>
  <Value className="java.lang.String"> </Value>
</Feature>
<Feature>
  <Name className="java.lang.String">length</Name>
  <Value className="java.lang.String">1</Value>
</Feature>
<Feature>
  <Name className="java.lang.String">kind</Name>
  <Value className="java.lang.String">space</Value>
</Feature>
</Annotation>
<Annotation Id="17" Type="Token" StartNode="47" EndNode="51">
<Feature>
  <Name className="java.lang.String">length</Name>
  <Value className="java.lang.String">4</Value>
</Feature>
<Feature>
  <Name className="java.lang.String">orth</Name>
  <Value className="java.lang.String">lowercase</Value>
</Feature>
<Feature>
  <Name className="java.lang.String">string</Name>
  <Value className="java.lang.String">test</Value>
</Feature>
<Feature>
  <Name className="java.lang.String">category</Name>
  <Value className="java.lang.String">NN</Value>
</Feature>
<Feature>
  <Name className="java.lang.String">kind</Name>
  <Value className="java.lang.String">word</Value>
</Feature>
</Annotation>
<Annotation Id="18" Type="SpaceToken" StartNode="51" EndNode="52">
<Feature>
  <Name className="java.lang.String">string</Name>
  <Value className="java.lang.String"> </Value>
</Feature>
<Feature>
  <Name className="java.lang.String">length</Name>
  <Value className="java.lang.String">1</Value>
</Feature>
<Feature>
  <Name className="java.lang.String">kind</Name>
  <Value className="java.lang.String">space</Value>
</Feature>
</Annotation>
<Annotation Id="19" Type="Token" StartNode="52" EndNode="59">
<Feature>
  <Name className="java.lang.String">length</Name>
  <Value className="java.lang.String">7</Value>
</Feature>
<Feature>
  <Name className="java.lang.String">orth</Name>
  <Value className="java.lang.String">lowercase</Value>
</Feature>
<Feature>
  <Name className="java.lang.String">string</Name>
  <Value className="java.lang.String">failure</Value>
</Feature>
<Feature>
  <Name className="java.lang.String">category</Name>
  <Value className="java.lang.String">NN</Value>
</Feature>
<Feature>
  <Name className="java.lang.String">kind</Name>
  <Value className="java.lang.String">word</Value>
</Feature>
</Annotation>
<Annotation Id="20" Type="SpaceToken" StartNode="59" EndNode="60">
<Feature>
  <Name className="java.lang.String">string</Name>
  <Value className="java.lang.String"> </Value>
</Feature>
<Feature>
  <Name className="java.lang.String">length</Name>
  <Value className="java.lang.String">1</Value>
</Feature>
<Feature>
  <Name className="java.lang.String">kind</Name>
  <Value className="java.lang.String">space</Value>
</Feature>
</Annotation>
<Annotation Id="21" Type="Token" StartNode="60" EndNode="64">
<Feature>
  <Name className="java.lang.String">length</Name>
  <Value className="java.lang.String">4</Value>
</Feature>
<Feature>
  <Name className="java.lang.String">orth</Name>
  <Value className="java.lang.String">lowercase</Value>
</Feature>
<Feature>
  <Name className="java.lang.String">string</Name>
  <Value className="java.lang.String">rate</Value>
</Feature>
<Feature>
  <Name className="java.lang.String">category</Name>
  <Value className="java.lang.String">NN</Value>
</Feature>
<Feature>
  <Name className="java.lang.String">kind</Name>
  <Value className="java.lang.String">word</Value>
</Feature>
</Annotation>
<Annotation Id="22" Type="Token" StartNode="64" EndNode="65">
<Feature>
  <Name className="java.lang.String">length</Name>
  <Value className="java.lang.String">1</Value>
</Feature>
<Feature>
  <Name className="java.lang.String">string</Name>
  <Value className="java.lang.String">:</Value>
</Feature>
<Feature>
  <Name className="java.lang.String">category</Name>
  <Value className="java.lang.String">:</Value>
</Feature>
<Feature>
  <Name className="java.lang.String">kind</Name>
  <Value className="java.lang.String">punctuation</Value>
</Feature>
</Annotation>
<Annotation Id="23" Type="SpaceToken" StartNode="65" EndNode="66">
<Feature>
  <Name className="java.lang.String">string</Name>
  <Value className="java.lang.String"> </Value>
</Feature>
<Feature>
  <Name className="java.lang.String">length</Name>
  <Value className="java.lang.String">1</Value>
</Feature>
<Feature>
  <Name className="java.lang.String">kind</Name>
  <Value className="java.lang.String">space</Value>
</Feature>
</Annotation>
<Annotation Id="24" Type="Token" StartNode="66" EndNode="71">
<Feature>
  <Name className="java.lang.String">length</Name>
  <Value className="java.lang.String">5</Value>
</Feature>
<Feature>
  <Name className="java.lang.String">orth</Name>
  <Value className="java.lang.String">upperInitial</Value>
</Feature>
<Feature>
  <Name className="java.lang.String">string</Name>
  <Value className="java.lang.String">Doing</Value>
</Feature>
<Feature>
  <Name className="java.lang.String">category</Name>
  <Value className="java.lang.String">VBG</Value>
</Feature>
<Feature>
  <Name className="java.lang.String">kind</Name>
  <Value className="java.lang.String">word</Value>
</Feature>
</Annotation>
<Annotation Id="25" Type="SpaceToken" StartNode="71" EndNode="72">
<Feature>
  <Name className="java.lang.String">string</Name>
  <Value className="java.lang.String"> </Value>
</Feature>
<Feature>
  <Name className="java.lang.String">length</Name>
  <Value className="java.lang.String">1</Value>
</Feature>
<Feature>
  <Name className="java.lang.String">kind</Name>
  <Value className="java.lang.String">space</Value>
</Feature>
</Annotation>
<Annotation Id="26" Type="Token" StartNode="72" EndNode="79">
<Feature>
  <Name className="java.lang.String">length</Name>
  <Value className="java.lang.String">7</Value>
</Feature>
<Feature>
  <Name className="java.lang.String">orth</Name>
  <Value className="java.lang.String">lowercase</Value>
</Feature>
<Feature>
  <Name className="java.lang.String">string</Name>
  <Value className="java.lang.String">nothing</Value>
</Feature>
<Feature>
  <Name className="java.lang.String">category</Name>
  <Value className="java.lang.String">NN</Value>
</Feature>
<Feature>
  <Name className="java.lang.String">kind</Name>
  <Value className="java.lang.String">word</Value>
</Feature>
</Annotation>
<Annotation Id="27" Type="SpaceToken" StartNode="79" EndNode="80">
<Feature>
  <Name className="java.lang.String">string</Name>
  <Value className="java.lang.String"> </Value>
</Feature>
<Feature>
  <Name className="java.lang.String">length</Name>
  <Value className="java.lang.String">1</Value>
</Feature>
<Feature>
  <Name className="java.lang.String">kind</Name>
  <Value className="java.lang.String">space</Value>
</Feature>
</Annotation>
<Annotation Id="28" Type="Token" StartNode="80" EndNode="85">
<Feature>
  <Name className="java.lang.String">length</Name>
  <Value className="java.lang.String">5</Value>
</Feature>
<Feature>
  <Name className="java.lang.String">orth</Name>
  <Value className="java.lang.String">lowercase</Value>
</Feature>
<Feature>
  <Name className="java.lang.String">string</Name>
  <Value className="java.lang.String">about</Value>
</Feature>
<Feature>
  <Name className="java.lang.String">category</Name>
  <Value className="java.lang.String">IN</Value>
</Feature>
<Feature>
  <Name className="java.lang.String">kind</Name>
  <Value className="java.lang.String">word</Value>
</Feature>
</Annotation>
<Annotation Id="29" Type="SpaceToken" StartNode="85" EndNode="86">
<Feature>
  <Name className="java.lang.String">string</Name>
  <Value className="java.lang.String"> </Value>
</Feature>
<Feature>
  <Name className="java.lang.String">length</Name>
  <Value className="java.lang.String">1</Value>
</Feature>
<Feature>
  <Name className="java.lang.String">kind</Name>
  <Value className="java.lang.String">space</Value>
</Feature>
</Annotation>
<Annotation Id="30" Type="Token" StartNode="86" EndNode="89">
<Feature>
  <Name className="java.lang.String">length</Name>
  <Value className="java.lang.String">3</Value>
</Feature>
<Feature>
  <Name className="java.lang.String">orth</Name>
  <Value className="java.lang.String">lowercase</Value>
</Feature>
<Feature>
  <Name className="java.lang.String">string</Name>
  <Value className="java.lang.String">the</Value>
</Feature>
<Feature>
  <Name className="java.lang.String">category</Name>
  <Value className="java.lang.String">DT</Value>
</Feature>
<Feature>
  <Name className="java.lang.String">kind</Name>
  <Value className="java.lang.String">word</Value>
</Feature>
</Annotation>
<Annotation Id="31" Type="SpaceToken" StartNode="89" EndNode="90">
<Feature>
  <Name className="java.lang.String">string</Name>
  <Value className="java.lang.String"> </Value>
</Feature>
<Feature>
  <Name className="java.lang.String">length</Name>
  <Value className="java.lang.String">1</Value>
</Feature>
<Feature>
  <Name className="java.lang.String">kind</Name>
  <Value className="java.lang.String">space</Value>
</Feature>
</Annotation>
<Annotation Id="32" Type="Token" StartNode="90" EndNode="96">
<Feature>
  <Name className="java.lang.String">length</Name>
  <Value className="java.lang.String">6</Value>
</Feature>
<Feature>
  <Name className="java.lang.String">orth</Name>
  <Value className="java.lang.String">lowercase</Value>
</Feature>
<Feature>
  <Name className="java.lang.String">string</Name>
  <Value className="java.lang.String">rising</Value>
</Feature>
<Feature>
  <Name className="java.lang.String">category</Name>
  <Value className="java.lang.String">VBG</Value>
</Feature>
<Feature>
  <Name className="java.lang.String">kind</Name>
  <Value className="java.lang.String">word</Value>
</Feature>
</Annotation>
<Annotation Id="33" Type="SpaceToken" StartNode="96" EndNode="97">
<Feature>
  <Name className="java.lang.String">string</Name>
  <Value className="java.lang.String"> </Value>
</Feature>
<Feature>
  <Name className="java.lang.String">length</Name>
  <Value className="java.lang.String">1</Value>
</Feature>
<Feature>
  <Name className="java.lang.String">kind</Name>
  <Value className="java.lang.String">space</Value>
</Feature>
</Annotation>
<Annotation Id="34" Type="Token" StartNode="97" EndNode="103">
<Feature>
  <Name className="java.lang.String">length</Name>
  <Value className="java.lang.String">6</Value>
</Feature>
<Feature>
  <Name className="java.lang.String">orth</Name>
  <Value className="java.lang.String">lowercase</Value>
</Feature>
<Feature>
  <Name className="java.lang.String">string</Name>
  <Value className="java.lang.String">number</Value>
</Feature>
<Feature>
  <Name className="java.lang.String">category</Name>
  <Value className="java.lang.String">NN</Value>
</Feature>
<Feature>
  <Name className="java.lang.String">kind</Name>
  <Value className="java.lang.String">word</Value>
</Feature>
</Annotation>
<Annotation Id="35" Type="SpaceToken" StartNode="103" EndNode="104">
<Feature>
  <Name className="java.lang.String">string</Name>
  <Value className="java.lang.String"> </Value>
</Feature>
<Feature>
  <Name className="java.lang.String">length</Name>
  <Value className="java.lang.String">1</Value>
</Feature>
<Feature>
  <Name className="java.lang.String">kind</Name>
  <Value className="java.lang.String">space</Value>
</Feature>
</Annotation>
<Annotation Id="36" Type="Token" StartNode="104" EndNode="106">
<Feature>
  <Name className="java.lang.String">length</Name>
  <Value className="java.lang.String">2</Value>
</Feature>
<Feature>
  <Name className="java.lang.String">orth</Name>
  <Value className="java.lang.String">lowercase</Value>
</Feature>
<Feature>
  <Name className="java.lang.String">string</Name>
  <Value className="java.lang.String">of</Value>
</Feature>
<Feature>
  <Name className="java.lang.String">category</Name>
  <Value className="java.lang.String">IN</Value>
</Feature>
<Feature>
  <Name className="java.lang.String">kind</Name>
  <Value className="java.lang.String">word</Value>
</Feature>
</Annotation>
<Annotation Id="37" Type="SpaceToken" StartNode="106" EndNode="107">
<Feature>
  <Name className="java.lang.String">string</Name>
  <Value className="java.lang.String"> </Value>
</Feature>
<Feature>
  <Name className="java.lang.String">length</Name>
  <Value className="java.lang.String">1</Value>
</Feature>
<Feature>
  <Name className="java.lang.String">kind</Name>
  <Value className="java.lang.String">space</Value>
</Feature>
</Annotation>
<Annotation Id="38" Type="Token" StartNode="107" EndNode="110">
<Feature>
  <Name className="java.lang.String">length</Name>
  <Value className="java.lang.String">3</Value>
</Feature>
<Feature>
  <Name className="java.lang.String">orth</Name>
  <Value className="java.lang.String">lowercase</Value>
</Feature>
<Feature>
  <Name className="java.lang.String">origString</Name>
  <Value className="java.lang.String">peo</Value>
</Feature>
<Feature>
  <Name className="java.lang.String">string</Name>
  <Value className="java.lang.String">peo</Value>
</Feature>
<Feature>
  <Name className="java.lang.String">category</Name>
  <Value className="java.lang.String">NN</Value>
</Feature>
<Feature>
  <Name className="java.lang.String">kind</Name>
  <Value className="java.lang.String">word</Value>
</Feature>
</Annotation>
<Annotation Id="39" Type="Token" StartNode="110" EndNode="111">
<Feature>
  <Name className="java.lang.String">length</Name>
  <Value className="java.lang.String">1</Value>
</Feature>
<Feature>
  <Name className="java.lang.String">string</Name>
  <Value className="java.lang.String">.</Value>
</Feature>
<Feature>
  <Name className="java.lang.String">category</Name>
  <Value className="java.lang.String">.</Value>
</Feature>
<Feature>
  <Name className="java.lang.String">kind</Name>
  <Value className="java.lang.String">punctuation</Value>
</Feature>
</Annotation>
<Annotation Id="40" Type="Token" StartNode="111" EndNode="112">
<Feature>
  <Name className="java.lang.String">length</Name>
  <Value className="java.lang.String">1</Value>
</Feature>
<Feature>
  <Name className="java.lang.String">string</Name>
  <Value className="java.lang.String">.</Value>
</Feature>
<Feature>
  <Name className="java.lang.String">category</Name>
  <Value className="java.lang.String">UH</Value>
</Feature>
<Feature>
  <Name className="java.lang.String">kind</Name>
  <Value className="java.lang.String">punctuation</Value>
</Feature>
</Annotation>
<Annotation Id="41" Type="Token" StartNode="112" EndNode="113">
<Feature>
  <Name className="java.lang.String">length</Name>
  <Value className="java.lang.String">1</Value>
</Feature>
<Feature>
  <Name className="java.lang.String">string</Name>
  <Value className="java.lang.String">.</Value>
</Feature>
<Feature>
  <Name className="java.lang.String">category</Name>
  <Value className="java.lang.String">.</Value>
</Feature>
<Feature>
  <Name className="java.lang.String">kind</Name>
  <Value className="java.lang.String">punctuation</Value>
</Feature>
</Annotation>
<Annotation Id="42" Type="SpaceToken" StartNode="113" EndNode="114">
<Feature>
  <Name className="java.lang.String">string</Name>
  <Value className="java.lang.String"> </Value>
</Feature>
<Feature>
  <Name className="java.lang.String">length</Name>
  <Value className="java.lang.String">1</Value>
</Feature>
<Feature>
  <Name className="java.lang.String">kind</Name>
  <Value className="java.lang.String">space</Value>
</Feature>
</Annotation>
<Annotation Id="56" Type="Token" StartNode="114" EndNode="136">
<Feature>
  <Name className="java.lang.String">string</Name>
  <Value className="java.lang.String">http://t.co/mfKI2KayVc</Value>
</Feature>
<Feature>
  <Name className="java.lang.String">kind</Name>
  <Value className="java.lang.String">URL</Value>
</Feature>
<Feature>
  <Name className="java.lang.String">temp_category</Name>
  <Value className="java.lang.String">NN</Value>
</Feature>
<Feature>
  <Name className="java.lang.String">length</Name>
  <Value className="java.lang.Long">22</Value>
</Feature>
<Feature>
  <Name className="java.lang.String">rule</Name>
  <Value className="java.lang.String">URL</Value>
</Feature>
<Feature>
  <Name className="java.lang.String">replaced</Name>
  <Value className="java.lang.Integer">11</Value>
</Feature>
<Feature>
  <Name className="java.lang.String">category</Name>
  <Value className="java.lang.String">URL</Value>
</Feature>
</Annotation>
<Annotation Id="58" Type="SpaceToken" StartNode="136" EndNode="137">
<Feature>
  <Name className="java.lang.String">string</Name>
  <Value className="java.lang.String">
</Value>
</Feature>
<Feature>
  <Name className="java.lang.String">length</Name>
  <Value className="java.lang.String">1</Value>
</Feature>
<Feature>
  <Name className="java.lang.String">kind</Name>
  <Value className="java.lang.String">control</Value>
</Feature>
</Annotation>
<Annotation Id="59" Type="SpaceToken" StartNode="137" EndNode="138">
<Feature>
  <Name className="java.lang.String">string</Name>
  <Value className="java.lang.String">
</Value>
</Feature>
<Feature>
  <Name className="java.lang.String">length</Name>
  <Value className="java.lang.String">1</Value>
</Feature>
<Feature>
  <Name className="java.lang.String">kind</Name>
  <Value className="java.lang.String">control</Value>
</Feature>
</Annotation>
<Annotation Id="191" Type="Person" StartNode="1" EndNode="9">
</Annotation>
</AnnotationSet>

<!-- Named annotation set -->

<AnnotationSet Name="Key">
<Annotation Id="1" Type="Tweet" StartNode="0" EndNode="137">
<Feature>
  <Name className="java.lang.String">user:screen_name</Name>
  <Value className="java.lang.String">newzealandnews</Value>
</Feature>
<Feature>
  <Name className="java.lang.String">id_str</Name>
  <Value className="java.lang.String">471798826898960384</Value>
</Feature>
<Feature>
  <Name className="java.lang.String">truncated</Name>
  <Value className="java.lang.Boolean">false</Value>
</Feature>
<Feature>
  <Name className="java.lang.String">user:location</Name>
  <Value className="java.lang.String">New Zealand</Value>
</Feature>
<Feature>
  <Name className="java.lang.String">source</Name>
  <Value className="java.lang.String">&lt;a href="http://twitterfeed.com" rel="nofollow">twitterfeed&lt;/a></Value>
</Feature>
<Feature>
  <Name className="java.lang.String">lang</Name>
  <Value className="java.lang.String">english</Value>
</Feature>
<Feature>
  <Name className="java.lang.String">_unit_id</Name>
  <Value className="java.lang.Long">935247621</Value>
</Feature>
<Feature>
  <Name className="java.lang.String">Location_unit_id</Name>
  <Value className="java.lang.Long">611231643</Value>
</Feature>
<Feature>
  <Name className="java.lang.String">Person_unit_id</Name>
  <Value className="java.lang.Long">611189648</Value>
</Feature>
</Annotation>
<Annotation Id="3" Type="Token" StartNode="0" EndNode="1">
<Feature>
  <Name className="java.lang.String">length</Name>
  <Value className="java.lang.String">1</Value>
</Feature>
<Feature>
  <Name className="java.lang.String">string</Name>
  <Value className="java.lang.String">'</Value>
</Feature>
<Feature>
  <Name className="java.lang.String">category</Name>
  <Value className="java.lang.String">''</Value>
</Feature>
<Feature>
  <Name className="java.lang.String">kind</Name>
  <Value className="java.lang.String">punctuation</Value>
</Feature>
</Annotation>
<Annotation Id="4" Type="Token" StartNode="1" EndNode="9">
<Feature>
  <Name className="java.lang.String">length</Name>
  <Value className="java.lang.String">8</Value>
</Feature>
<Feature>
  <Name className="java.lang.String">orth</Name>
  <Value className="java.lang.String">upperInitial</Value>
</Feature>
<Feature>
  <Name className="java.lang.String">string</Name>
  <Value className="java.lang.String">Brownlee</Value>
</Feature>
<Feature>
  <Name className="java.lang.String">category</Name>
  <Value className="java.lang.String">NNP</Value>
</Feature>
<Feature>
  <Name className="java.lang.String">kind</Name>
  <Value className="java.lang.String">word</Value>
</Feature>
</Annotation>
<Annotation Id="5" Type="SpaceToken" StartNode="9" EndNode="10">
<Feature>
  <Name className="java.lang.String">string</Name>
  <Value className="java.lang.String"> </Value>
</Feature>
<Feature>
  <Name className="java.lang.String">length</Name>
  <Value className="java.lang.String">1</Value>
</Feature>
<Feature>
  <Name className="java.lang.String">kind</Name>
  <Value className="java.lang.String">space</Value>
</Feature>
</Annotation>
<Annotation Id="6" Type="Token" StartNode="10" EndNode="15">
<Feature>
  <Name className="java.lang.String">length</Name>
  <Value className="java.lang.String">5</Value>
</Feature>
<Feature>
  <Name className="java.lang.String">orth</Name>
  <Value className="java.lang.String">lowercase</Value>
</Feature>
<Feature>
  <Name className="java.lang.String">string</Name>
  <Value className="java.lang.String">doing</Value>
</Feature>
<Feature>
  <Name className="java.lang.String">category</Name>
  <Value className="java.lang.String">VBG</Value>
</Feature>
<Feature>
  <Name className="java.lang.String">kind</Name>
  <Value className="java.lang.String">word</Value>
</Feature>
</Annotation>
<Annotation Id="7" Type="SpaceToken" StartNode="15" EndNode="16">
<Feature>
  <Name className="java.lang.String">string</Name>
  <Value className="java.lang.String"> </Value>
</Feature>
<Feature>
  <Name className="java.lang.String">length</Name>
  <Value className="java.lang.String">1</Value>
</Feature>
<Feature>
  <Name className="java.lang.String">kind</Name>
  <Value className="java.lang.String">space</Value>
</Feature>
</Annotation>
<Annotation Id="8" Type="Token" StartNode="16" EndNode="23">
<Feature>
  <Name className="java.lang.String">length</Name>
  <Value className="java.lang.String">7</Value>
</Feature>
<Feature>
  <Name className="java.lang.String">orth</Name>
  <Value className="java.lang.String">lowercase</Value>
</Feature>
<Feature>
  <Name className="java.lang.String">string</Name>
  <Value className="java.lang.String">nothing</Value>
</Feature>
<Feature>
  <Name className="java.lang.String">category</Name>
  <Value className="java.lang.String">NN</Value>
</Feature>
<Feature>
  <Name className="java.lang.String">kind</Name>
  <Value className="java.lang.String">word</Value>
</Feature>
</Annotation>
<Annotation Id="9" Type="Token" StartNode="23" EndNode="24">
<Feature>
  <Name className="java.lang.String">length</Name>
  <Value className="java.lang.String">1</Value>
</Feature>
<Feature>
  <Name className="java.lang.String">string</Name>
  <Value className="java.lang.String">'</Value>
</Feature>
<Feature>
  <Name className="java.lang.String">category</Name>
  <Value className="java.lang.String">''</Value>
</Feature>
<Feature>
  <Name className="java.lang.String">kind</Name>
  <Value className="java.lang.String">punctuation</Value>
</Feature>
</Annotation>
<Annotation Id="10" Type="SpaceToken" StartNode="24" EndNode="25">
<Feature>
  <Name className="java.lang.String">string</Name>
  <Value className="java.lang.String"> </Value>
</Feature>
<Feature>
  <Name className="java.lang.String">length</Name>
  <Value className="java.lang.String">1</Value>
</Feature>
<Feature>
  <Name className="java.lang.String">kind</Name>
  <Value className="java.lang.String">space</Value>
</Feature>
</Annotation>
<Annotation Id="11" Type="Token" StartNode="25" EndNode="30">
<Feature>
  <Name className="java.lang.String">length</Name>
  <Value className="java.lang.String">5</Value>
</Feature>
<Feature>
  <Name className="java.lang.String">orth</Name>
  <Value className="java.lang.String">lowercase</Value>
</Feature>
<Feature>
  <Name className="java.lang.String">string</Name>
  <Value className="java.lang.String">about</Value>
</Feature>
<Feature>
  <Name className="java.lang.String">category</Name>
  <Value className="java.lang.String">IN</Value>
</Feature>
<Feature>
  <Name className="java.lang.String">kind</Name>
  <Value className="java.lang.String">word</Value>
</Feature>
</Annotation>
<Annotation Id="12" Type="SpaceToken" StartNode="30" EndNode="31">
<Feature>
  <Name className="java.lang.String">string</Name>
  <Value className="java.lang.String"> </Value>
</Feature>
<Feature>
  <Name className="java.lang.String">length</Name>
  <Value className="java.lang.String">1</Value>
</Feature>
<Feature>
  <Name className="java.lang.String">kind</Name>
  <Value className="java.lang.String">space</Value>
</Feature>
</Annotation>
<Annotation Id="13" Type="Token" StartNode="31" EndNode="38">
<Feature>
  <Name className="java.lang.String">length</Name>
  <Value className="java.lang.String">7</Value>
</Feature>
<Feature>
  <Name className="java.lang.String">orth</Name>
  <Value className="java.lang.String">lowercase</Value>
</Feature>
<Feature>
  <Name className="java.lang.String">string</Name>
  <Value className="java.lang.String">driving</Value>
</Feature>
<Feature>
  <Name className="java.lang.String">category</Name>
  <Value className="java.lang.String">VBG</Value>
</Feature>
<Feature>
  <Name className="java.lang.String">kind</Name>
  <Value className="java.lang.String">word</Value>
</Feature>
</Annotation>
<Annotation Id="14" Type="SpaceToken" StartNode="38" EndNode="39">
<Feature>
  <Name className="java.lang.String">string</Name>
  <Value className="java.lang.String"> </Value>
</Feature>
<Feature>
  <Name className="java.lang.String">length</Name>
  <Value className="java.lang.String">1</Value>
</Feature>
<Feature>
  <Name className="java.lang.String">kind</Name>
  <Value className="java.lang.String">space</Value>
</Feature>
</Annotation>
<Annotation Id="15" Type="Token" StartNode="39" EndNode="46">
<Feature>
  <Name className="java.lang.String">length</Name>
  <Value className="java.lang.String">7</Value>
</Feature>
<Feature>
  <Name className="java.lang.String">orth</Name>
  <Value className="java.lang.String">lowercase</Value>
</Feature>
<Feature>
  <Name className="java.lang.String">string</Name>
  <Value className="java.lang.String">licence</Value>
</Feature>
<Feature>
  <Name className="java.lang.String">category</Name>
  <Value className="java.lang.String">NN</Value>
</Feature>
<Feature>
  <Name className="java.lang.String">kind</Name>
  <Value className="java.lang.String">word</Value>
</Feature>
</Annotation>
<Annotation Id="16" Type="SpaceToken" StartNode="46" EndNode="47">
<Feature>
  <Name className="java.lang.String">string</Name>
  <Value className="java.lang.String"> </Value>
</Feature>
<Feature>
  <Name className="java.lang.String">length</Name>
  <Value className="java.lang.String">1</Value>
</Feature>
<Feature>
  <Name className="java.lang.String">kind</Name>
  <Value className="java.lang.String">space</Value>
</Feature>
</Annotation>
<Annotation Id="17" Type="Token" StartNode="47" EndNode="51">
<Feature>
  <Name className="java.lang.String">length</Name>
  <Value className="java.lang.String">4</Value>
</Feature>
<Feature>
  <Name className="java.lang.String">orth</Name>
  <Value className="java.lang.String">lowercase</Value>
</Feature>
<Feature>
  <Name className="java.lang.String">string</Name>
  <Value className="java.lang.String">test</Value>
</Feature>
<Feature>
  <Name className="java.lang.String">category</Name>
  <Value className="java.lang.String">NN</Value>
</Feature>
<Feature>
  <Name className="java.lang.String">kind</Name>
  <Value className="java.lang.String">word</Value>
</Feature>
</Annotation>
<Annotation Id="18" Type="SpaceToken" StartNode="51" EndNode="52">
<Feature>
  <Name className="java.lang.String">string</Name>
  <Value className="java.lang.String"> </Value>
</Feature>
<Feature>
  <Name className="java.lang.String">length</Name>
  <Value className="java.lang.String">1</Value>
</Feature>
<Feature>
  <Name className="java.lang.String">kind</Name>
  <Value className="java.lang.String">space</Value>
</Feature>
</Annotation>
<Annotation Id="19" Type="Token" StartNode="52" EndNode="59">
<Feature>
  <Name className="java.lang.String">length</Name>
  <Value className="java.lang.String">7</Value>
</Feature>
<Feature>
  <Name className="java.lang.String">orth</Name>
  <Value className="java.lang.String">lowercase</Value>
</Feature>
<Feature>
  <Name className="java.lang.String">string</Name>
  <Value className="java.lang.String">failure</Value>
</Feature>
<Feature>
  <Name className="java.lang.String">category</Name>
  <Value className="java.lang.String">NN</Value>
</Feature>
<Feature>
  <Name className="java.lang.String">kind</Name>
  <Value className="java.lang.String">word</Value>
</Feature>
</Annotation>
<Annotation Id="20" Type="SpaceToken" StartNode="59" EndNode="60">
<Feature>
  <Name className="java.lang.String">string</Name>
  <Value className="java.lang.String"> </Value>
</Feature>
<Feature>
  <Name className="java.lang.String">length</Name>
  <Value className="java.lang.String">1</Value>
</Feature>
<Feature>
  <Name className="java.lang.String">kind</Name>
  <Value className="java.lang.String">space</Value>
</Feature>
</Annotation>
<Annotation Id="21" Type="Token" StartNode="60" EndNode="64">
<Feature>
  <Name className="java.lang.String">length</Name>
  <Value className="java.lang.String">4</Value>
</Feature>
<Feature>
  <Name className="java.lang.String">orth</Name>
  <Value className="java.lang.String">lowercase</Value>
</Feature>
<Feature>
  <Name className="java.lang.String">string</Name>
  <Value className="java.lang.String">rate</Value>
</Feature>
<Feature>
  <Name className="java.lang.String">category</Name>
  <Value className="java.lang.String">NN</Value>
</Feature>
<Feature>
  <Name className="java.lang.String">kind</Name>
  <Value className="java.lang.String">word</Value>
</Feature>
</Annotation>
<Annotation Id="22" Type="Token" StartNode="64" EndNode="65">
<Feature>
  <Name className="java.lang.String">length</Name>
  <Value className="java.lang.String">1</Value>
</Feature>
<Feature>
  <Name className="java.lang.String">string</Name>
  <Value className="java.lang.String">:</Value>
</Feature>
<Feature>
  <Name className="java.lang.String">category</Name>
  <Value className="java.lang.String">:</Value>
</Feature>
<Feature>
  <Name className="java.lang.String">kind</Name>
  <Value className="java.lang.String">punctuation</Value>
</Feature>
</Annotation>
<Annotation Id="23" Type="SpaceToken" StartNode="65" EndNode="66">
<Feature>
  <Name className="java.lang.String">string</Name>
  <Value className="java.lang.String"> </Value>
</Feature>
<Feature>
  <Name className="java.lang.String">length</Name>
  <Value className="java.lang.String">1</Value>
</Feature>
<Feature>
  <Name className="java.lang.String">kind</Name>
  <Value className="java.lang.String">space</Value>
</Feature>
</Annotation>
<Annotation Id="24" Type="Token" StartNode="66" EndNode="71">
<Feature>
  <Name className="java.lang.String">length</Name>
  <Value className="java.lang.String">5</Value>
</Feature>
<Feature>
  <Name className="java.lang.String">orth</Name>
  <Value className="java.lang.String">upperInitial</Value>
</Feature>
<Feature>
  <Name className="java.lang.String">string</Name>
  <Value className="java.lang.String">Doing</Value>
</Feature>
<Feature>
  <Name className="java.lang.String">category</Name>
  <Value className="java.lang.String">VBG</Value>
</Feature>
<Feature>
  <Name className="java.lang.String">kind</Name>
  <Value className="java.lang.String">word</Value>
</Feature>
</Annotation>
<Annotation Id="25" Type="SpaceToken" StartNode="71" EndNode="72">
<Feature>
  <Name className="java.lang.String">string</Name>
  <Value className="java.lang.String"> </Value>
</Feature>
<Feature>
  <Name className="java.lang.String">length</Name>
  <Value className="java.lang.String">1</Value>
</Feature>
<Feature>
  <Name className="java.lang.String">kind</Name>
  <Value className="java.lang.String">space</Value>
</Feature>
</Annotation>
<Annotation Id="26" Type="Token" StartNode="72" EndNode="79">
<Feature>
  <Name className="java.lang.String">length</Name>
  <Value className="java.lang.String">7</Value>
</Feature>
<Feature>
  <Name className="java.lang.String">orth</Name>
  <Value className="java.lang.String">lowercase</Value>
</Feature>
<Feature>
  <Name className="java.lang.String">string</Name>
  <Value className="java.lang.String">nothing</Value>
</Feature>
<Feature>
  <Name className="java.lang.String">category</Name>
  <Value className="java.lang.String">NN</Value>
</Feature>
<Feature>
  <Name className="java.lang.String">kind</Name>
  <Value className="java.lang.String">word</Value>
</Feature>
</Annotation>
<Annotation Id="27" Type="SpaceToken" StartNode="79" EndNode="80">
<Feature>
  <Name className="java.lang.String">string</Name>
  <Value className="java.lang.String"> </Value>
</Feature>
<Feature>
  <Name className="java.lang.String">length</Name>
  <Value className="java.lang.String">1</Value>
</Feature>
<Feature>
  <Name className="java.lang.String">kind</Name>
  <Value className="java.lang.String">space</Value>
</Feature>
</Annotation>
<Annotation Id="28" Type="Token" StartNode="80" EndNode="85">
<Feature>
  <Name className="java.lang.String">length</Name>
  <Value className="java.lang.String">5</Value>
</Feature>
<Feature>
  <Name className="java.lang.String">orth</Name>
  <Value className="java.lang.String">lowercase</Value>
</Feature>
<Feature>
  <Name className="java.lang.String">string</Name>
  <Value className="java.lang.String">about</Value>
</Feature>
<Feature>
  <Name className="java.lang.String">category</Name>
  <Value className="java.lang.String">IN</Value>
</Feature>
<Feature>
  <Name className="java.lang.String">kind</Name>
  <Value className="java.lang.String">word</Value>
</Feature>
</Annotation>
<Annotation Id="29" Type="SpaceToken" StartNode="85" EndNode="86">
<Feature>
  <Name className="java.lang.String">string</Name>
  <Value className="java.lang.String"> </Value>
</Feature>
<Feature>
  <Name className="java.lang.String">length</Name>
  <Value className="java.lang.String">1</Value>
</Feature>
<Feature>
  <Name className="java.lang.String">kind</Name>
  <Value className="java.lang.String">space</Value>
</Feature>
</Annotation>
<Annotation Id="30" Type="Token" StartNode="86" EndNode="89">
<Feature>
  <Name className="java.lang.String">length</Name>
  <Value className="java.lang.String">3</Value>
</Feature>
<Feature>
  <Name className="java.lang.String">orth</Name>
  <Value className="java.lang.String">lowercase</Value>
</Feature>
<Feature>
  <Name className="java.lang.String">string</Name>
  <Value className="java.lang.String">the</Value>
</Feature>
<Feature>
  <Name className="java.lang.String">category</Name>
  <Value className="java.lang.String">DT</Value>
</Feature>
<Feature>
  <Name className="java.lang.String">kind</Name>
  <Value className="java.lang.String">word</Value>
</Feature>
</Annotation>
<Annotation Id="31" Type="SpaceToken" StartNode="89" EndNode="90">
<Feature>
  <Name className="java.lang.String">string</Name>
  <Value className="java.lang.String"> </Value>
</Feature>
<Feature>
  <Name className="java.lang.String">length</Name>
  <Value className="java.lang.String">1</Value>
</Feature>
<Feature>
  <Name className="java.lang.String">kind</Name>
  <Value className="java.lang.String">space</Value>
</Feature>
</Annotation>
<Annotation Id="32" Type="Token" StartNode="90" EndNode="96">
<Feature>
  <Name className="java.lang.String">length</Name>
  <Value className="java.lang.String">6</Value>
</Feature>
<Feature>
  <Name className="java.lang.String">orth</Name>
  <Value className="java.lang.String">lowercase</Value>
</Feature>
<Feature>
  <Name className="java.lang.String">string</Name>
  <Value className="java.lang.String">rising</Value>
</Feature>
<Feature>
  <Name className="java.lang.String">category</Name>
  <Value className="java.lang.String">VBG</Value>
</Feature>
<Feature>
  <Name className="java.lang.String">kind</Name>
  <Value className="java.lang.String">word</Value>
</Feature>
</Annotation>
<Annotation Id="33" Type="SpaceToken" StartNode="96" EndNode="97">
<Feature>
  <Name className="java.lang.String">string</Name>
  <Value className="java.lang.String"> </Value>
</Feature>
<Feature>
  <Name className="java.lang.String">length</Name>
  <Value className="java.lang.String">1</Value>
</Feature>
<Feature>
  <Name className="java.lang.String">kind</Name>
  <Value className="java.lang.String">space</Value>
</Feature>
</Annotation>
<Annotation Id="34" Type="Token" StartNode="97" EndNode="103">
<Feature>
  <Name className="java.lang.String">length</Name>
  <Value className="java.lang.String">6</Value>
</Feature>
<Feature>
  <Name className="java.lang.String">orth</Name>
  <Value className="java.lang.String">lowercase</Value>
</Feature>
<Feature>
  <Name className="java.lang.String">string</Name>
  <Value className="java.lang.String">number</Value>
</Feature>
<Feature>
  <Name className="java.lang.String">category</Name>
  <Value className="java.lang.String">NN</Value>
</Feature>
<Feature>
  <Name className="java.lang.String">kind</Name>
  <Value className="java.lang.String">word</Value>
</Feature>
</Annotation>
<Annotation Id="35" Type="SpaceToken" StartNode="103" EndNode="104">
<Feature>
  <Name className="java.lang.String">string</Name>
  <Value className="java.lang.String"> </Value>
</Feature>
<Feature>
  <Name className="java.lang.String">length</Name>
  <Value className="java.lang.String">1</Value>
</Feature>
<Feature>
  <Name className="java.lang.String">kind</Name>
  <Value className="java.lang.String">space</Value>
</Feature>
</Annotation>
<Annotation Id="36" Type="Token" StartNode="104" EndNode="106">
<Feature>
  <Name className="java.lang.String">length</Name>
  <Value className="java.lang.String">2</Value>
</Feature>
<Feature>
  <Name className="java.lang.String">orth</Name>
  <Value className="java.lang.String">lowercase</Value>
</Feature>
<Feature>
  <Name className="java.lang.String">string</Name>
  <Value className="java.lang.String">of</Value>
</Feature>
<Feature>
  <Name className="java.lang.String">category</Name>
  <Value className="java.lang.String">IN</Value>
</Feature>
<Feature>
  <Name className="java.lang.String">kind</Name>
  <Value className="java.lang.String">word</Value>
</Feature>
</Annotation>
<Annotation Id="37" Type="SpaceToken" StartNode="106" EndNode="107">
<Feature>
  <Name className="java.lang.String">string</Name>
  <Value className="java.lang.String"> </Value>
</Feature>
<Feature>
  <Name className="java.lang.String">length</Name>
  <Value className="java.lang.String">1</Value>
</Feature>
<Feature>
  <Name className="java.lang.String">kind</Name>
  <Value className="java.lang.String">space</Value>
</Feature>
</Annotation>
<Annotation Id="38" Type="Token" StartNode="107" EndNode="110">
<Feature>
  <Name className="java.lang.String">length</Name>
  <Value className="java.lang.String">3</Value>
</Feature>
<Feature>
  <Name className="java.lang.String">orth</Name>
  <Value className="java.lang.String">lowercase</Value>
</Feature>
<Feature>
  <Name className="java.lang.String">origString</Name>
  <Value className="java.lang.String">peo</Value>
</Feature>
<Feature>
  <Name className="java.lang.String">string</Name>
  <Value className="java.lang.String">peo</Value>
</Feature>
<Feature>
  <Name className="java.lang.String">category</Name>
  <Value className="java.lang.String">NN</Value>
</Feature>
<Feature>
  <Name className="java.lang.String">kind</Name>
  <Value className="java.lang.String">word</Value>
</Feature>
</Annotation>
<Annotation Id="39" Type="Token" StartNode="110" EndNode="111">
<Feature>
  <Name className="java.lang.String">length</Name>
  <Value className="java.lang.String">1</Value>
</Feature>
<Feature>
  <Name className="java.lang.String">string</Name>
  <Value className="java.lang.String">.</Value>
</Feature>
<Feature>
  <Name className="java.lang.String">category</Name>
  <Value className="java.lang.String">.</Value>
</Feature>
<Feature>
  <Name className="java.lang.String">kind</Name>
  <Value className="java.lang.String">punctuation</Value>
</Feature>
</Annotation>
<Annotation Id="40" Type="Token" StartNode="111" EndNode="112">
<Feature>
  <Name className="java.lang.String">length</Name>
  <Value className="java.lang.String">1</Value>
</Feature>
<Feature>
  <Name className="java.lang.String">string</Name>
  <Value className="java.lang.String">.</Value>
</Feature>
<Feature>
  <Name className="java.lang.String">category</Name>
  <Value className="java.lang.String">UH</Value>
</Feature>
<Feature>
  <Name className="java.lang.String">kind</Name>
  <Value className="java.lang.String">punctuation</Value>
</Feature>
</Annotation>
<Annotation Id="41" Type="Token" StartNode="112" EndNode="113">
<Feature>
  <Name className="java.lang.String">length</Name>
  <Value className="java.lang.String">1</Value>
</Feature>
<Feature>
  <Name className="java.lang.String">string</Name>
  <Value className="java.lang.String">.</Value>
</Feature>
<Feature>
  <Name className="java.lang.String">category</Name>
  <Value className="java.lang.String">.</Value>
</Feature>
<Feature>
  <Name className="java.lang.String">kind</Name>
  <Value className="java.lang.String">punctuation</Value>
</Feature>
</Annotation>
<Annotation Id="42" Type="SpaceToken" StartNode="113" EndNode="114">
<Feature>
  <Name className="java.lang.String">string</Name>
  <Value className="java.lang.String"> </Value>
</Feature>
<Feature>
  <Name className="java.lang.String">length</Name>
  <Value className="java.lang.String">1</Value>
</Feature>
<Feature>
  <Name className="java.lang.String">kind</Name>
  <Value className="java.lang.String">space</Value>
</Feature>
</Annotation>
<Annotation Id="176" Type="Lookup" StartNode="123" EndNode="125">
<Feature>
  <Name className="java.lang.String">majorType</Name>
  <Value className="java.lang.String">country_code</Value>
</Feature>
</Annotation>
<Annotation Id="177" Type="Lookup" StartNode="123" EndNode="125">
<Feature>
  <Name className="java.lang.String">majorType</Name>
  <Value className="java.lang.String">url_key</Value>
</Feature>
</Annotation>
<Annotation Id="178" Type="Split" StartNode="110" EndNode="113">
<Feature>
  <Name className="java.lang.String">kind</Name>
  <Value className="java.lang.String">internal</Value>
</Feature>
</Annotation>
<Annotation Id="179" Type="Split" StartNode="136" EndNode="138">
<Feature>
  <Name className="java.lang.String">kind</Name>
  <Value className="java.lang.String">external</Value>
</Feature>
</Annotation>
<Annotation Id="180" Type="Sentence" StartNode="0" EndNode="113">
</Annotation>
<Annotation Id="181" Type="Sentence" StartNode="114" EndNode="136">
</Annotation>
<Annotation Id="56" Type="Token" StartNode="114" EndNode="136">
<Feature>
  <Name className="java.lang.String">string</Name>
  <Value className="java.lang.String">http://t.co/mfKI2KayVc</Value>
</Feature>
<Feature>
  <Name className="java.lang.String">kind</Name>
  <Value className="java.lang.String">URL</Value>
</Feature>
<Feature>
  <Name className="java.lang.String">temp_category</Name>
  <Value className="java.lang.String">NN</Value>
</Feature>
<Feature>
  <Name className="java.lang.String">length</Name>
  <Value className="java.lang.Long">22</Value>
</Feature>
<Feature>
  <Name className="java.lang.String">rule</Name>
  <Value className="java.lang.String">URL</Value>
</Feature>
<Feature>
  <Name className="java.lang.String">replaced</Name>
  <Value className="java.lang.Integer">11</Value>
</Feature>
<Feature>
  <Name className="java.lang.String">category</Name>
  <Value className="java.lang.String">URL</Value>
</Feature>
</Annotation>
<Annotation Id="57" Type="URL" StartNode="114" EndNode="136">
<Feature>
  <Name className="java.lang.String">string</Name>
  <Value className="java.lang.String">http://t.co/mfKI2KayVc</Value>
</Feature>
<Feature>
  <Name className="java.lang.String">kind</Name>
  <Value className="java.lang.String">URL</Value>
</Feature>
<Feature>
  <Name className="java.lang.String">temp_category</Name>
  <Value className="java.lang.String">NN</Value>
</Feature>
<Feature>
  <Name className="java.lang.String">length</Name>
  <Value className="java.lang.Long">22</Value>
</Feature>
<Feature>
  <Name className="java.lang.String">rule</Name>
  <Value className="java.lang.String">URL</Value>
</Feature>
<Feature>
  <Name className="java.lang.String">replaced</Name>
  <Value className="java.lang.Integer">11</Value>
</Feature>
<Feature>
  <Name className="java.lang.String">category</Name>
  <Value className="java.lang.String">URL</Value>
</Feature>
</Annotation>
<Annotation Id="58" Type="SpaceToken" StartNode="136" EndNode="137">
<Feature>
  <Name className="java.lang.String">string</Name>
  <Value className="java.lang.String">
</Value>
</Feature>
<Feature>
  <Name className="java.lang.String">length</Name>
  <Value className="java.lang.String">1</Value>
</Feature>
<Feature>
  <Name className="java.lang.String">kind</Name>
  <Value className="java.lang.String">control</Value>
</Feature>
</Annotation>
<Annotation Id="59" Type="SpaceToken" StartNode="137" EndNode="138">
<Feature>
  <Name className="java.lang.String">string</Name>
  <Value className="java.lang.String">
</Value>
</Feature>
<Feature>
  <Name className="java.lang.String">length</Name>
  <Value className="java.lang.String">1</Value>
</Feature>
<Feature>
  <Name className="java.lang.String">kind</Name>
  <Value className="java.lang.String">control</Value>
</Feature>
</Annotation>
<Annotation Id="188" Type="Unknown" StartNode="1" EndNode="9">
<Feature>
  <Name className="java.lang.String">rule</Name>
  <Value className="java.lang.String">Unknown</Value>
</Feature>
<Feature>
  <Name className="java.lang.String">kind</Name>
  <Value className="java.lang.String">PN</Value>
</Feature>
</Annotation>
</AnnotationSet>

</GateDocument>
